Workbook

Sheet Basic
B1: Font | C1: blue | D1: Historical Numbers | G1: 2025-26
G2: Q1
B3: Font | C3: black | D3: Calculation & formula | G3: 2024-25
G4: Q1 | H4: Q2 | I4: Q3 | J4: Q4
B5: Font | C5: red | D5: Verification | G5: 2023-24
G6: Q1 | H6: Q2 | I6: Q3 | J6: Q4
B7: Font | C7: green | D7: Referencing | G7: 2022-23
G8: Q1 | H8: Q2 | I8: Q3 | J8: Q4
B9: Font | C9: blue | D9: Projection / Guidance
B10: Background

Sheet Income Statement
B1: FY Mar Rs. Lakhs | C1: FY 2020-21 | D1: Q1 2021-22 | E1: Q2 2021-22 | F1: Q3 2021-22 | G1: Q4 2021-22 | H1: FY 2021-22 | I1: Q1 2022-23 | J1: Q2 2022-23 | K1: Q3 2022-23 | L1: Q4 2022-23 | M1: FY 2022-23 | N1: Q1 2023-24 | O1: Q2 2023-24 | P1: Q3 2023-24 | Q1: Q4 2023-24 | R1: FY 2023-24 | S1: Q1 2024-25 | T1: Q2 2024-25 | U1: Q3 2024-25 | V1: Q4 2024-25 | W1: FY 2024-25 | X1: Q1 2025-26 | Y1: E Q2 2025-26 | Z1: E Q3 2025-26 | AA1: E Q4 2025-26 | AB1: E FY 2025-26 | AC1: E FY 2026-27 | AD1: E FY 2027-28 | AE1: E FY 2028-29 | AF1: FY 2029-30
B3: Revenue from Operations | C3: 288053 | D3: 66095 | E3: 78884 | F3: 97185 | G3: 77039 | H3: 319203 | I3: 77331 | J3: 81375 | K3: 98272 | L3: 83595 | M3: 340573 | N3: 82566 | O3: 86487 | P3: 99632 | Q3: 89124 | R3: 357809 | S3: 90607 | T3: 89059 | U3: 104948 | V3: 96305 | W3: 380919 | X3: 90409 | Y3: ='Revenue Tab'!Y2 -> 96323.04 | Z3: ='Revenue Tab'!Z2 -> 112401.7 | AA3: ='Revenue Tab'!AA2 -> 103932.58 | AB3: ='Revenue Tab'!AB2 -> 405225.31 | AC3: ='Revenue Tab'!AC2 -> 427917.93 | AD3: ='Revenue Tab'!AD2 -> 451881.33 | AE3: ='Revenue Tab'!AE2 -> 477186.69 | AF3: ='Revenue Tab'!AF2 -> 503909.14
A4: Add | B4: Other Income | C4: 7027 | D4: 1072 | E4: 3761 | F4: 1663 | G4: 3029 | H4: 9525 | I4: 633 | J4: 4199 | K4: 686 | L4: 1375 | M4: 6893 | N4: 828 | O4: 1111 | P4: 1671 | Q4: 1070 | R4: 4680 | S4: 1046 | T4: 2156 | U4: 1493 | V4: 2116 | W4: 6811 | X4: 2159 | Y4: ='Revenue Tab'!Y9 -> 1926.4608 | Z4: ='Revenue Tab'!Z9 -> 2248.0339 | AA4: ='Revenue Tab'!AA9 -> 2078.6515 | AB4: ='Revenue Tab'!AB9 -> 8412.1462 | AC4: ='Revenue Tab'!AC9 -> 8558.3586 | AD4: ='Revenue Tab'!AD9 -> 9037.6267 | AE4: ='Revenue Tab'!AE9 -> 9543.7338 | AF4: ='Revenue Tab'!AF9 -> 10078.183
A5: Add | B5: Total revenue from operations | C5: =C3+C4 -> 295080 | D5: =D3+D4 -> 67167 | E5: =E3+E4 -> 82645 | F5: =F3+F4 -> 98848 | G5: =G3+G4 -> 80068 | H5: =H3+H4 -> 328728 | I5: =I3+I4 -> 77964 | J5: =J3+J4 -> 85574 | ... X5: =X3+X4 -> 92568 | Y5: ='Revenue Tab'!Y11 -> 98249.501 | Z5: ='Revenue Tab'!Z11 -> 114649.73 | AA5: ='Revenue Tab'!AA11 -> 106011.23 | AB5: ='Revenue Tab'!AB11 -> 413637.46 | AC5: ='Revenue Tab'!AC11 -> 436476.29 | AD5: ='Revenue Tab'!AD11 -> 460918.96 | AE5: ='Revenue Tab'!AE11 -> 486730.42 | AF5: ='Revenue Tab'!AF11 -> 513987.33
B6: YOY | H6: =H5/C5-1 -> 0.11403009 | I6: =I5/D5-1 -> 0.16074858 | J6: =J5/E5-1 -> 0.035440741 | K6: =K5/F5-1 -> 0.0011128197 | L6: =L5/G5-1 -> 0.06122296 | M6: =M5/H5-1 -> 0.057001533 | N6: =N5/I5-1 -> 0.06964753 | O6: =O5/J5-1 -> 0.023652044 | ... X6: =X5/S5-1 -> 0.0099833066
B7: QoQ | E7: =E5/D5-1 -> 0.23044054 | F7: =F5/E5-1 -> 0.19605542 | G7: =G5/F5-1 -> -0.18998867 | J7: =J5/I5-1 -> 0.097609153 | K7: =K5/J5-1 -> 0.15640265 | L7: =L5/K5-1 -> -0.1413529 | O7: =O5/N5-1 -> 0.050411301 | P7: =P5/O5-1 -> 0.15645334 | Q7: =Q5/P5-1 -> -0.10966112 | T7: =T5/S5-1 -> -0.0047788943 | U7: =U5/T5-1 -> 0.1669243 | V7: =V5/U5-1 -> -0.075346906 | X7: =X5/W5-1 -> -0.76125654
A9: Add | B9: Checkline | C9: =C3+C4 -> 295080 | D9: =D3+D4 -> 67167 | E9: =E3+E4 -> 82645 | F9: =F3+F4 -> 98848 | G9: =G3+G4 -> 80068 | H9: =H3+H4 -> 328728 | I9: =I3+I4 -> 77964 | J9: =J3+J4 -> 85574 | ... AF9: =AF3+AF4 -> 513987.33
B10: Cost of material consumed | C10: 70855 | D10: 18394 | E10: 24793 | F10: 24356 | G10: 22487 | H10: 90030 | I10: 16342 | J10: 24765 | K10: 23419 | L10: 18446 | M10: 82474 | N10: 16395 | O10: 21471 | P10: 20292 | Q10: 18726 | R10: 76884 | S10: 13994 | T10: 20737 | U10: 21468 | V10: 16214 | W10: 72413 | X10: 16356 | Y10: ='Expense Tab'!Y2 -> 18294.057 | Z10: ='Expense Tab'!Z2 -> 21347.78 | AA10: ='Expense Tab'!AA2 -> 19739.291 | AB10: ='Expense Tab'!AB2 -> 75737.127 | AC10: ='Expense Tab'!AC2 -> 81271.885 | AD10: ='Expense Tab'!AD2 -> 85823.11 | AE10: ='Expense Tab'!AE2 -> 90629.205 | AF10: ='Expense Tab'!AF2 -> 95704.44
B11: Purchase of stock in trade | C11: 24009 | D11: 4331 | E11: 2754 | F11: 4800 | G11: 10462 | H11: 22347 | I11: 6585 | J11: 7536 | K11: 6208 | L11: 13640 | M11: 33969 | N11: 9852 | O11: 9053 | P11: 8994 | Q11: 12824 | R11: 40723 | S11: 11388 | T11: 9938 | U11: 8682 | V11: 14824 | W11: 44832 | X11: 10857 | Y11: ='Expense Tab'!Y4 -> 9628.4511 | Z11: ='Expense Tab'!Z4 -> 11235.674 | AA11: ='Expense Tab'!AA4 -> 10389.1 | AB11: ='Expense Tab'!AB4 -> 42110.225 | AC11: ='Expense Tab'!AC4 -> 42774.676 | AD11: ='Expense Tab'!AD4 -> 45170.058 | AE11: ='Expense Tab'!AE4 -> 47699.581 | AF11: ='Expense Tab'!AF4 -> 50370.758
B12: (Increase)/Decrease in Inventories of Finished Goods, Stock in Trade and Work-in-Progress | C12: -1940 | D12: -263 | E12: -2909 | F12: 2543 | G12: -3960 | H12: -4589 | I12: 6180 | J12: -5144 | K12: 3926 | L12: -1269 | M12: 3693 | N12: 2312 | O12: -4654 | P12: 1835 | Q12: -1055 | R12: -1553 | S12: 3915 | T12: -4573 | U12: 1031 | V12: 1805 | W12: 2178 | X12: 433 | Y12: ='Expense Tab'!Y6 -> 20219.747 | Z12: ='Expense Tab'!Z6 -> 23594.914 | AA12: ='Expense Tab'!AA6 -> 21817.111 | AB12: ='Expense Tab'!AB6 -> 66064.772 | AC12: ='Expense Tab'!AC6 -> 89826.82 | AD12: ='Expense Tab'!AD6 -> 94857.122 | AE12: ='Expense Tab'!AE6 -> 100169.12 | AF12: ='Expense Tab'!AF6 -> 105778.59
B13: advertisment and sale | C13: 45813 | D13: 10986 | E13: 10532 | F13: 15825 | G13: 14947 | H13: 52290 | I13: 13630 | J13: 14148 | K13: 15326 | L13: 12966 | M13: 56070 | N13: 15187 | O13: 15441 | P13: 16573 | Q13: 18019 | R13: 65220 | S13: 18369 | T13: 14572 | U13: 17573 | V13: 18888 | W13: 69402 | X13: 17975 | Y13: ='Expense Tab'!Y7 -> 16368.367 | Z13: ='Expense Tab'!Z7 -> 19100.645 | AA13: ='Expense Tab'!AA7 -> 17661.471 | AB13: ='Expense Tab'!AB7 -> 71105.482 | AC13: ='Expense Tab'!AC7 -> 72716.95 | AD13: ='Expense Tab'!AD7 -> 76789.099 | AE13: ='Expense Tab'!AE7 -> 81089.288 | AF13: ='Expense Tab'!AF7 -> 85630.288
B14: COGS | C14: =C10+C11+C12+C13 -> 138737 | D14: =D10+D11+D12+D13 -> 33448 | E14: =E10+E11+E12+E13 -> 35170 | F14: =F10+F11+F12+F13 -> 47524 | G14: =G10+G11+G12+G13 -> 43936 | H14: =H10+H11+H12+H13 -> 160078 | I14: =I10+I11+I12+I13 -> 42737 | J14: =J10+J11+J12+J13 -> 41305 | ... X14: =X10+X11+X12+X13 -> 45621 | Y14: ='Expense Tab'!Y9 -> 48142.255 | Z14: ='Expense Tab'!Z9 -> 56178.368 | AA14: ='Expense Tab'!AA9 -> 51945.501 | AB14: ='Expense Tab'!AB9 -> 201887.12 | AC14: ='Expense Tab'!AC9 -> 213873.38 | AD14: ='Expense Tab'!AD9 -> 225850.29 | AE14: ='Expense Tab'!AE9 -> 238497.91 | AF14: ='Expense Tab'!AF9 -> 251853.79
B15: Gross profit | C15: =C5-C14 -> 156343 | D15: =D5-D14 -> 33719 | E15: =E5-E14 -> 47475 | F15: =F5-F14 -> 51324 | G15: =G5-G14 -> 36132 | H15: =H5-H14 -> 168650 | I15: =I5-I14 -> 35227 | J15: =J5-J14 -> 44269 | ... AF15: =AF5-AF14 -> 262133.54
B16: Gross profit Margin % | C16: =C15/C5 -> 0.52983259 | D16: =D15/D5 -> 0.50201736 | E16: =E15/E5 -> 0.57444491 | F16: =F15/F5 -> 0.51922143 | G16: =G15/G5 -> 0.45126642 | H16: =H15/H5 -> 0.51303813 | I16: =I15/I5 -> 0.45183675 | J16: =J15/J5 -> 0.51731834 | ... AF16: =AF15/AF5 -> 0.51
B18: Employee Benefits Expenses | C18: 30917 | D18: 8450 | E18: 8207 | F18: 7235 | G18: 7885 | H18: 31777 | I18: 8879 | J18: 9347 | K18: 9343 | L18: 9207 | M18: 36776 | N18: 10141 | O18: 10166 | P18: 10208 | Q18: 9049 | R18: =SUM(N18:Q18) -> 39564 | S18: 11106 | T18: 11287 | U18: 11246 | V18: 11063 | W18: 44702 | X18: 11946 | Y18: ='Expense Tab'!Y11 -> 10807.445 | Z18: ='Expense Tab'!Z11 -> 12611.47 | AA18: ='Expense Tab'!AA11 -> 11661.235 | AB18: ='Expense Tab'!AB11 -> 47026.15 | AC18: ='Expense Tab'!AC11 -> 48012.392 | AD18: ='Expense Tab'!AD11 -> 50701.086 | AE18: ='Expense Tab'!AE11 -> 53540.346 | AF18: ='Expense Tab'!AF11 -> 56538.606
B19: Other Expenses | C19: 30094 | D19: 7226 | E19: 7789 | F19: 8272 | G19: 8824 | H19: 32111 | I19: 8881 | J19: 11185 | K19: 10625 | L19: 10624 | M19: 41315 | N19: 9678 | O19: 11634 | P19: 10243 | Q19: 10463 | R19: 42018 | S19: 10184 | T19: 12051 | U19: 11079 | V19: 11567 | W19: 44881 | X19: 11420 | Y19: ='Expense Tab'!Y13 -> 10375.147 | Z19: ='Expense Tab'!Z13 -> 12107.011 | AA19: ='Expense Tab'!AA13 -> 11194.786 | AB19: ='Expense Tab'!AB13 -> 45096.944 | AC19: ='Expense Tab'!AC13 -> 46091.896 | AD19: ='Expense Tab'!AD13 -> 48673.042 | AE19: ='Expense Tab'!AE13 -> 51398.733 | AF19: ='Expense Tab'!AF13 -> 54277.062
B20: Operating Expenses | C20: =C18+C19 -> 61011 | D20: =D18+D19 -> 15676 | E20: =E18+E19 -> 15996 | F20: =F18+F19 -> 15507 | G20: =G18+G19 -> 16709 | H20: =H18+H19 -> 63888 | I20: =I18+I19 -> 17760 | J20: =J18+J19 -> 20532 | ... X20: =X18+X19 -> 23366 | Y20: ='Expense Tab'!Y15 -> 21614.89 | Z20: ='Expense Tab'!Z15 -> 25222.941 | AA20: ='Expense Tab'!AA15 -> 23322.47 | AB20: ='Expense Tab'!AB15 -> 93526.301 | AC20: ='Expense Tab'!AC15 -> 96024.783 | AD20: ='Expense Tab'!AD15 -> 101402.17 | AE20: ='Expense Tab'!AE15 -> 107080.69 | AF20: ='Expense Tab'!AF15 -> 113077.21
B22: EBITDA | C22: =C15-C20 -> 95332 | D22: =D15-D20 -> 18043 | E22: =E15-E20 -> 31479 | F22: =F15-F20 -> 35817 | G22: =G15-G20 -> 19423 | H22: =H15-H20 -> 104762 | I22: =I15-I20 -> 17467 | J22: =J15-J20 -> 23737 | ... X22: =X15-X20 -> 23581 | AB22: =AB15-AB20 -> 118224.03 | AC22: =AC15-AC20 -> 126578.12 | AD22: =AD15-AD20 -> 133666.5 | AE22: =AE15-AE20 -> 141151.82 | AF22: =AF15-AF20 -> 149056.32
B23: EBITDA Margin % | C23: =C22/C5 -> 0.32307171 | D23: =D22/D5 -> 0.26862894 | E23: =E22/E5 -> 0.38089419 | F23: =F22/F5 -> 0.36234421 | G23: =G22/G5 -> 0.24258131 | H23: =H22/H5 -> 0.31868901 | I23: =I22/I5 -> 0.2240393 | J23: =J22/J5 -> 0.27738565 | ... X23: =X22/X5 -> 0.25474246 | AB23: =AB22/AB5 -> 0.28581559 | AC23: =AC22/AC5 -> 0.29 | AD23: =AD22/AD5 -> 0.29 | AE23: =AE22/AE5 -> 0.29 | AF23: =AF22/AF5 -> 0.29
B24: Depreciation | C24: =9248+662 -> 9910 | D24: =2170+169 -> 2339 | E24: =2191+170 -> 2361 | F24: =2181+237 -> 2418 | G24: =2140+163 -> 2303 | H24: =8682+739 -> 9421 | I24: =2215+201 -> 2416 | J24: =2194+253 -> 2447 | K24: =2123+255 -> 2378 | L24: =2237+258 -> 2495 | M24: =8769+967 -> 9736 | N24: =1964+318 -> 2282 | O24: =1950+317 -> 2267 | P24: =1924+315 -> 2239 | Q24: =7046+1520 -> 8566 | R24: =7863+1409 -> 9272 | S24: =1764+357 -> 2121 | T24: =1789+346 -> 2135 | U24: =1827+405 -> 2232 | V24: =1666+412 -> 2078 | W24: =7046+1520 -> 8566 | X24: =1756+416 -> 2172 | AB24: ='D&A'!AB6 -> 7895.9387 | AC24: ='D&A'!AC6 -> 7436.795 | AD24: ='D&A'!AD6 -> 7083.6671 | AE24: ='D&A'!AE6 -> 6821.1827 | AF24: ='D&A'!AF6 -> 6636.1985
B25: Amortization | C25: 26785 | D25: 5961 | E25: 6027 | F25: 6026 | G25: 6043 | H25: 24057 | I25: 6395 | J25: 2346 | K25: 2346 | L25: 3902 | M25: 14989 | N25: 2318 | O25: 2342 | P25: 2342 | Q25: 2316 | R25: 9318 | S25: 2322 | T25: 2230 | U25: 2328 | V25: 2275 | W25: 9255 | X25: 2278 | AB25: ='D&A'!AB14 -> 9355 | AC25: ='D&A'!AC14 -> 2378 | AD25: ='D&A'!AD14 -> 2478 | AE25: ='D&A'!AE14 -> 2578 | AF25: ='D&A'!AF14 -> 2678
B26: D&A | C26: =C24+C25 -> 36695 | D26: =D24+D25 -> 8300 | E26: =E24+E25 -> 8388 | F26: =F24+F25 -> 8444 | G26: =G24+G25 -> 8346 | H26: =H24+H25 -> 33478 | I26: =I24+I25 -> 8811 | J26: =J24+J25 -> 4793 | ... X26: =X24+X25 -> 4450 | AB26: =AB24+AB25 -> 17250.939 | AC26: =AC24+AC25 -> 9814.795 | AD26: =AD24+AD25 -> 9561.6671 | AE26: =AE24+AE25 -> 9399.1827 | AF26: =AF24+AF25 -> 9314.1985
B28: EBIT | C28: =C22-C26 -> 58637 | D28: =D22-D26 -> 9743 | E28: =E22-E26 -> 23091 | F28: =F22-F26 -> 27373 | G28: =G22-G26 -> 11077 | H28: =H22-H26 -> 71284 | I28: =I22-I26 -> 8656 | J28: =J22-J26 -> 18944 | ... X28: =X22-X26 -> 19131 | AB28: =AB22-AB26 -> 100973.09 | AC28: =AC22-AC26 -> 116763.33 | AD28: =AD22-AD26 -> 124104.83 | AE28: =AE22-AE26 -> 131752.64 | AF28: =AF22-AF26 -> 139742.13
B29: EBIT Margin | C29: =C28/C5 -> 0.1987156 | D29: =D28/D5 -> 0.14505635 | E29: =E28/E5 -> 0.27939984 | F29: =F28/F5 -> 0.27692012 | G29: =G28/G5 -> 0.13834491 | H29: =H28/H5 -> 0.21684797 | I29: =I28/I5 -> 0.1110256 | J29: =J28/J5 -> 0.22137565 | ... X29: =X28/X5 -> 0.20666969 | AB29: =AB28/AB5 -> 0.24411013 | AC29: =AC28/AC5 -> 0.26751357 | AD29: =AD28/AD5 -> 0.26925521 | AE29: =AE28/AE5 -> 0.27068914 | AF29: =AF28/AF5 -> 0.27187854
B31: Finance Costs | C31: 1327 | D31: 64 | E31: 78 | F31: 183 | G31: 182 | H31: 507 | I31: 249 | J31: 176 | K31: 177 | L31: 137 | M31: 739 | N31: 214 | O31: 225 | P31: 271 | Q31: 288 | R31: 998 | S31: 206 | T31: 233 | U31: 217 | V31: 278 | W31: 934 | X31: 243 | AB31: =DEBT!AB12 -> 789.2952 | AC31: =DEBT!AC12 -> 857.2952 | AD31: =DEBT!AD12 -> 925.2952 | AE31: =DEBT!AE12 -> 993.2952 | AF31: =DEBT!AF12 -> 1061.2952
A32: Less | B32: Share of Loss of Associates | C32: -418 | D32: -152 | E32: -384 | F32: -329 | G32: -593 | H32: -1458 | I32: -437 | J32: -216 | K32: -62 | L32: -35 | M32: -750 | N32: -50 | O32: -62 | P32: -103 | Q32: -157 | R32: -373 | S32: -210 | T32: -462 | U32: -450 | V32: -59 | W32: -1181 | X32: -211 | AB32: 0 | AC32: 0 | AD32: 0 | AE32: 0 | AF32: 0
B33: Exceptional Items | R33: -590 | AB33: 0 | AC33: 0 | AD33: 0 | AF33: 0
B34: PBT | C34: =C28-C31+C32+C33 -> 56892 | D34: =D28-D31+D32+D33 -> 9527 | E34: =E28-E31+E32+E33 -> 22629 | F34: =F28-F31+F32+F33 -> 26861 | G34: =G28-G31+G32+G33 -> 10302 | H34: =H28-H31+H32+H33 -> 69319 | I34: =I28-I31+I32+I33 -> 7970 | J34: =J28-J31+J32+J33 -> 18552 | ... X34: =X28-X31+X32+X33 -> 18677 | AB34: =AB28-AB31+AB32+AB33 -> 100183.8 | AC34: =AC28-AC31+AC32+AC33 -> 115906.03 | AD34: =AD28-AD31+AD32+AD33 -> 123179.54 | AE34: =AE28-AE31+AE32+AE33 -> 130759.34 | AF34: =AF28-AF31+AF32+AF33 -> 138680.83
B35: Checkline | C35: =C28-C31+C32+C33 -> 56892 | D35: =D28-D31+D32+D33 -> 9527 | E35: =E28-E31+E32+E33 -> 22629 | F35: =F28-F31+F32+F33 -> 26861 | G35: =G28-G31+G32+G33 -> 10302 | H35: =H28-H31+H32+H33 -> 69319 | I35: =I28-I31+I32+I33 -> 7970 | J35: =J28-J31+J32+J33 -> 18552 | ... X35: =X28-X31+X32+X33 -> 18677 | AB35: =AB28-AB31+AB32+AB33 -> 100183.8 | AC35: =AC28-AC31+AC32+AC33 -> 115906.03 | AD35: =AD28-AD31+AD32+AD33 -> 123179.54 | AE35: =AE28-AE31+AE32+AE33 -> 130759.34 | AF35: =AF28-AF31+AF32+AF33 -> 138680.83
B36: Tax | C36: =11474-53 -> 11421 | D36: =2131-383 -> 1748 | E36: =4106-2 -> 4104 | F36: =4915-6 -> 4909 | G36: =2387+795-5776-23033 -> -25627 | H36: =13539+404-5776 -> 8167 | I36: =2387+795-5776-23033 -> -25627 | J36: =2907-229-2139 -> 539 | K36: =4750+67-2966 -> 1851 | L36: =2912-201-2086 -> 625 | M36: =12678-8554+90 -> 4214 | N36: =2774-335-1149 -> 1290 | O36: =3362+58+(-2137) -> 1283 | P36: =4676-37-3091 -> 1548 | Q36: =3353+186+(-1291) -> 2248 | R36: =14465-7668-128 -> 6669 | S36: =3910-15-1117 -> 2778 | T36: =4031-320-2767 -> 944 | U36: =5717-345-3135 -> 2237 | V36: =4214+311+(-1372) -> 3153 | W36: =17872-8391-369 -> 9112 | X36: =3642-352-1039 -> 2251 | AB36: =AB34*AB37 -> 10018.38 | AC36: =AC34*AC37 -> 11590.603 | AD36: =AD34*AD37 -> 12317.954 | AE36: =AE34*AE37 -> 13075.934 | AF36: =AF34*AF37 -> 13868.083
B37: Tax Rate % | C37: =C36/C34 -> 0.20074879 | D37: =D36/D34 -> 0.18347853 | E37: =E36/E34 -> 0.1813602 | F37: =F36/F34 -> 0.18275567 | G37: =G36/G34 -> -2.4875752 | H37: =H36/H34 -> 0.11781763 | I37: =I36/I34 -> -3.2154329 | J37: =J36/J34 -> 0.029053471 | ... X37: =X36/X34 -> 0.12052257 | AB37: 0.1 | AC37: 0.1 | AD37: 0.1 | AE37: 0.1 | AF37: 0.1
A38: Less | B38: Net Profit | C38: =C34-C36 -> 45471 | D38: =D34-D36 -> 7779 | E38: =E34-E36 -> 18525 | F38: =F34-F36 -> 21952 | G38: =G34-G36 -> 35929 | H38: =H34-H36 -> 61152 | I38: =I34-I36 -> 33597 | J38: =J34-J36 -> 18013 | ... X38: =X34-X36 -> 16426 | AB38: =AB34-AB36 -> 90165.419 | AC38: =AC34-AC36 -> 104315.43 | AD38: =AD34-AD36 -> 110861.58 | AE38: =AE34-AE36 -> 117683.41 | AF38: =AF34-AF36 -> 124812.75
A39: Add | B39: Y0Y | H39: =H38/C38-1 -> 0.34485716 | M39: =M38/H38-1 -> 0.025984432 | R39: =R38/M38-1 -> 0.15415757 | W39: =W38/R38-1 -> 0.10855786 | AB39: =AB38/W38-1 -> 0.12322071 | AC39: =AC38/AB38-1 -> 0.1569339 | AD39: =AD38/AC38-1 -> 0.062753445 | AE39: =AE38/AD38-1 -> 0.061534639 | AF39: =AF38/AE38-1 -> 0.060580651
B40: Net Profit margin % | C40: =C38/C5 -> 0.15409719 | D40: =D38/D5 -> 0.1158158 | E40: =E38/E5 -> 0.22415149 | F40: =F38/F5 -> 0.22207834 | G40: =G38/G5 -> 0.44873108 | H40: =H38/H5 -> 0.18602614 | I40: =I38/I5 -> 0.43092966 | J40: =J38/J5 -> 0.21049618 | ... X40: =X38/X5 -> 0.17744793 | AB40: =AB38/AB5 -> 0.21798175 | AC40: =AC38/AC5 -> 0.23899449 | AD40: =AD38/AD5 -> 0.24052294 | AE40: =AE38/AE5 -> 0.24178355 | AF40: =AF38/AF5 -> 0.24283235
B41: Checkline | C41: =C34-C36 -> 45471 | D41: =D34-D36 -> 7779 | E41: =E34-E36 -> 18525 | F41: =F34-F36 -> 21952 | G41: =G34-G36 -> 35929 | H41: =H34-H36 -> 61152 | I41: =I34-I36 -> 33597 | J41: =J34-J36 -> 18013 | ... X41: =X34-X36 -> 16426 | AB41: =AB34-AB36 -> 90165.419 | AC41: =AC34-AC36 -> 104315.43 | AD41: =AD34-AD36 -> 110861.58 | AE41: =AE34-AE36 -> 117683.41 | AF41: =AF34-AF36 -> 124812.75

Sheet Balance Sheet
B1: FY Mar Rs. Lakhs | C1: FY 2020-21 | D1: Q1 2021-22 | E1: Q2 2021-22 | F1: Q3 2021-22 | G1: Q4 2021-22 | H1: FY 2021-22 | I1: Q1 2022-23 | J1: Q2 2022-23 | K1: Q3 2022-23 | L1: Q4 2022-23 | M1: FY 2022-23 | N1: Q1 2023-24 | O1: Q2 2023-24 | P1: Q3 2023-24 | Q1: Q4 2023-24 | R1: FY 2023-24 | S1: Q1 2024-25 | T1: Q2 2024-25 | U1: Q3 2024-25 | V1: Q4 2024-25 | W1: FY 2024-25 | X1: Q1 2025-26 | Y1: E FY 2025-26 | Z1: E FY 2026-27 | AA1: E FY 2027-28 | AB1: E FY 2028-29 | AC1: FY 2029-30
B2: Assets
B3: Property, Plant and Equipment | C3: 71426.68 | H3: 68569.04 | M3: 63005.53 | R3: 58114.73 | W3: 54454.75
B4: Capital Work in Progress | C4: 581.54 | H4: 172.3 | M4: 575.3 | R4: 672.49 | W4: 1327.55
B5: Investment Property | C5: 5304.07 | H5: 5412.69 | M5: 5338.9 | R5: 5198.57 | W5: 5108.09
B6: Goodwill on Consoildation | C6: 0 | H6: 2415.35 | M6: 6819 | R6: 6819 | W6: 6819
B7: Other Intangible Assets | C7: 35343.51 | H7: 56011.26 | M7: 47524.47 | R7: 38322.97 | W7: 29221.5
B8: Right of use of Assets | C8: 1109.06 | H8: 1983.7 | M8: 1847.04 | R8: 2908.07 | W8: 2834.14
B9: Intangible Assets under development | C9: 61.83 | H9: 135.41 | M9: 57.32 | R9: 82.29 | W9: 168.83
B10: Investment accounted for using equity method | C10: 0 | H10: 0 | M10: 0 | R10: 11678.26 | W10: 11189
B11: Financial Assets
B12: Investments | C12: =1762.78+14879.15 -> 16641.93 | H12: =5605.5+20711 -> 26316.5 | M12: =1086.77+16912 -> 17998.77 | R12: 16371.31 | W12: 13982.54
B13: Loans | C13: 574.46 | H13: 475 | M13: 169.46 | R13: 186.85 | W13: 524.68
B14: Other financial Assets | C14: 6716.48 | H14: 7673.07 | M14: 1991.81 | R14: 1273.49 | W14: 1019.93
B15: Deffered Tax Asset (Net) | C15: 0 | H15: 28380.81 | M15: 36367.67 | R15: 43792.52 | W15: 52393.25
B16: Non Current Tax Assets (Net) | C16: 37.99 | H16: 0 | M16: 0 | R16: 0 | W16: 0
B17: Other Non Current Assets | C17: 1492.35 | H17: 927.24 | M17: 608.51 | R17: 727.96 | W17: 952.88
B18: Total non-current assets | C18: =SUM(C3:C17) -> 139289.9 | D18: =SUM(D3:D17) -> 0 | E18: =SUM(E3:E17) -> 0 | F18: =SUM(F3:F17) -> 0 | G18: =SUM(G3:G17) -> 0 | H18: =SUM(H3:H17) -> 198472.37 | I18: =SUM(I3:I17) -> 0 | J18: =SUM(J3:J17) -> 0 | ... R18: =SUM(R3:R17) -> 186148.51 | W18: =SUM(W3:W17) -> 179996.14
B20: Inventories | C20: 30044.65 | H20: 35761.43 | M20: 32803.93 | R20: 32340.13 | W20: 30810.26
B21: Financial Assets
B22: Investments | C22: 8890.65 | H22: 3951.69 | M22: 11336.88 | R22: 16103.95 | W22: 42401.7
B23: Trade Receivables | C23: 23175.31 | H23: 32091.87 | M23: 41460.36 | R23: 49421.47 | W23: 45129.45
B24: Cash and Cash equivalents | C24: 1981.15 | H24: 2757.29 | M24: 4678.5 | R24: 5295.39 | W24: 10462.51
B25: Bank balance and other than above | C25: 34056.15 | H25: 8843.07 | M25: 13795.57 | R25: 14842.62 | W25: 16827.5
B26: Loans | C26: 302.88 | H26: 376.01 | M26: 599.45 | R26: 417.33 | W26: 420.2
B27: Other Financial Assets | C27: 3625.45 | H27: 4567.9 | M27: 7133.47 | R27: 7243.55 | W27: 12954.46
B28: Current Tax Assets (Net) | C28: 0 | H28: 84.71 | M28: 69.05 | R28: 92.61 | W28: 45.17
B29: Other Current Assets | C29: 10602.75 | H29: 18841.03 | M29: 16804.19 | R29: 16064.64 | W29: 14315.13
B30: Total current assets | C30: =SUM(C20:C29) -> 112678.99 | D30: =SUM(D20:D29) -> 0 | E30: =SUM(E20:E29) -> 0 | F30: =SUM(F20:F29) -> 0 | G30: =SUM(G20:G29) -> 0 | H30: =SUM(H20:H29) -> 107275 | I30: =SUM(I20:I29) -> 0 | J30: =SUM(J20:J29) -> 0 | ... R30: =SUM(R20:R29) -> 141821.69 | W30: =SUM(W20:W29) -> 173366.38
B32: TOTAL ASSETS | C32: =C30+C18 -> 251968.89 | D32: =D30+D18 -> 0 | E32: =E30+E18 -> 0 | F32: =F30+F18 -> 0 | G32: =G30+G18 -> 0 | H32: =H30+H18 -> 305747.37 | I32: =I30+I18 -> 0 | J32: =J30+J18 -> 0 | ... R32: =R30+R18 -> 327970.2 | W32: =W30+W18 -> 353362.52
B34: EQUITY AND LIABILITIES
B35: Equity
B36: Equity share capital | C36: 4445.14 | H36: 4411.5 | M36: 4411.5 | R36: 4365 | W36: 4365 | Y36: ='Equity Scheduled'!AB3 -> 4365 | Z36: ='Equity Scheduled'!AC3 -> 4365 | AA36: ='Equity Scheduled'!AD3 -> 4365 | AB36: ='Equity Scheduled'!AE3 -> 4365 | AC36: ='Equity Scheduled'!AF3 -> 4365
B37: Other equity | C37: 171819.86 | H37: 203247.87 | M37: 225868.49 | R37: 240293.79 | W37: 265114.29 | Y37: ='Equity Scheduled'!AB4 -> 310197 | Z37: ='Equity Scheduled'!AC4 -> 362354.71 | AA37: ='Equity Scheduled'!AD4 -> 417785.51 | AB37: ='Equity Scheduled'!AE4 -> 476627.21 | AC37: ='Equity Scheduled'!AF4 -> 539033.58
B38: Total Equity attributable to Equity Holders of the Parent | C38: =C37+C36 -> 176265 | D38: =D37+D36 -> 0 | E38: =E37+E36 -> 0 | F38: =F37+F36 -> 0 | G38: =G37+G36 -> 0 | H38: =H37+H36 -> 207659.37 | I38: =I37+I36 -> 0 | J38: =J37+J36 -> 0 | ... R38: =R37+R36 -> 244658.79 | W38: =W37+W36 -> 269479.29 | Y38: ='Equity Scheduled'!AB5 -> 314562 | Z38: ='Equity Scheduled'!AC5 -> 366719.71 | AA38: ='Equity Scheduled'!AD5 -> 422150.51 | AB38: ='Equity Scheduled'!AE5 -> 480992.21 | AC38: ='Equity Scheduled'!AF5 -> 543398.58
B39: Non-Controlling Interest | C39: -88.71 | H39: -230.09 | M39: 996.48 | R39: 1112.22 | W39: -143.43 | Y39: ='Equity Scheduled'!AB6 -> 51 | Z39: ='Equity Scheduled'!AC6 -> 51 | AA39: ='Equity Scheduled'!AD6 -> 51 | AB39: ='Equity Scheduled'!AE6 -> 51 | AC39: ='Equity Scheduled'!AF6 -> 51
B40: Total Equity | C40: =C38+C39 -> 176176.29 | D40: =D38+D39 -> 0 | E40: =E38+E39 -> 0 | F40: =F38+F39 -> 0 | G40: =G38+G39 -> 0 | H40: =H38+H39 -> 207429.28 | I40: =I38+I39 -> 0 | J40: =J38+J39 -> 0 | ... R40: =R38+R39 -> 245771.01 | W40: =W38+W39 -> 269335.86 | Y40: ='Equity Scheduled'!AB7 -> 314613 | Z40: ='Equity Scheduled'!AC7 -> 366770.71 | AA40: ='Equity Scheduled'!AD7 -> 422201.51 | AB40: ='Equity Scheduled'!AE7 -> 481043.21 | AC40: ='Equity Scheduled'!AF7 -> 543449.58
B42: Liabilities
B43: Non Current Liabilities
B44: Financial Liabilities
B45: Lease Liabilities | C45: 420.17 | H45: 988.36 | M45: 904.85 | R45: 1543.19 | W45: 1728.19
B46: Other financial Liabilities | C46: 669.01 | H46: 690.74 | M46: 687.96 | R46: 686.25 | W46: 304.27
B47: Provisions | C47: 2296.58 | H47: 2523.13 | M47: 2769.92 | R47: 1532.08 | W47: 1929.19
B48: Deffered Tax Liabilities (Net) | C48: 416.35 | H48: 754.01 | M48: 1344.48 | R48: 1088.44 | W48: 840.68
B49: Other Non Current financial Liabilities | C49: 1973.33 | H49: 1790.52 | M49: 1612.97 | R49: 1466.57 | W49: 1289.42
B50: Total non-current liabilities | C50: =SUM(C45:C49) -> 5775.44 | D50: =SUM(D45:D49) -> 0 | E50: =SUM(E45:E49) -> 0 | F50: =SUM(F45:F49) -> 0 | G50: =SUM(G45:G49) -> 0 | H50: =SUM(H45:H49) -> 6746.76 | I50: =SUM(I45:I49) -> 0 | J50: =SUM(J45:J49) -> 0 | ... R50: =SUM(R45:R49) -> 6316.53 | W50: =SUM(W45:W49) -> 6091.75
B51: Current Liabilities
B52: Financial Liabilities
B53: Borrowings | C53: 9190.93 | H53: 26371.12 | M53: 7360.85 | R53: 6568.92 | W53: 6208.47
B54: Lease Liability | C54: 463.33 | H54: 796.06 | M54: 785.1 | R54: 1283.48 | W54: 1042.43
B55: Trade Payables
B56: Total outstanding dues of Micro Enterprises & Small Enterprises | C56: 1213.83 | H56: 3369.6 | M56: 3128.01 | R56: 3631.39 | W56: 5606.74
B57: Total outstanding dues of creditors other than Micro Enterprises & Small Enterprises | C57: 33853.72 | H57: 37503.85 | M57: 38501.53 | R57: 41827.39 | W57: 37953.17
B58: Other Financial Liabilities | C58: 5632.76 | H58: 4644.64 | M58: 5133.59 | R58: 5670.62 | W58: 12578.92
B59: Other Current Liabilities | C59: 3008.24 | H59: 2543.22 | M59: 3014.65 | R59: 3430.67 | W59: 4229.4
B60: Provisions | C60: 14284.79 | H60: 14641.92 | M60: 11899.69 | R60: 11028.83 | W60: 8532.38
B61: Current Tax Liabilities (Net) | C61: 2369.56 | H61: 1702.04 | M61: 2565.13 | R61: 2441.36 | W61: 1783.41
B62: Total Current Liabilities | C62: =SUM(C53:C61) -> 70017.16 | D62: =SUM(D53:D61) -> 0 | E62: =SUM(E53:E61) -> 0 | F62: =SUM(F53:F61) -> 0 | G62: =SUM(G53:G61) -> 0 | H62: =SUM(H53:H61) -> 91572.45 | I62: =SUM(I53:I61) -> 0 | J62: =SUM(J53:J61) -> 0 | ... R62: =SUM(R53:R61) -> 75882.66 | W62: =SUM(W53:W61) -> 77934.92
B63: TOTAL EQUITY AND LIABILITIES | C63: =C40+C50+C62 -> 251968.89 | D63: =D40+D50+D62 -> 0 | E63: =E40+E50+E62 -> 0 | F63: =F40+F50+F62 -> 0 | G63: =G40+G50+G62 -> 0 | H63: =H40+H50+H62 -> 305748.49 | I63: =I40+I50+I62 -> 0 | J63: =J40+J50+J62 -> 0 | ... Q63: =Q40+Q50+Q62 -> 0 | R63: =R62+R50+R40 -> 327970.2 | W63: =W40+W50+W62 -> 353362.53

Sheet Cash Flow 
B1: FY Mar Rs. Lakhs | C1: FY 2020-21 | D1: Q1 2021-22 | E1: Q2 2021-22 | F1: Q3 2021-22 | G1: Q4 2021-22 | H1: FY 2021-22 | I1: Q1 2022-23 | J1: Q2 2022-23 | K1: Q3 2022-23 | L1: Q4 2022-23 | M1: FY 2022-23 | N1: Q1 2023-24 | O1: Q2 2023-24 | P1: Q3 2023-24 | Q1: Q4 2023-24 | R1: FY 2023-24 | S1: Q1 2024-25 | T1: Q2 2024-25 | U1: Q3 2024-25 | V1: Q4 2024-25 | W1: FY 2024-25 | X1: E Q2 2025-26 | Y1: E Q3 2025-26 | Z1: E Q4 2025-26 | AA1: E FY 2025-26 | AB1: E FY 2026-27 | AC1: E FY 2027-28 | AD1: E FY 2028-29 | AE1: FY 2029-30
B3: A. Cash Flows from Operating Activities | C3: 56892.14 | H3: 68800.5 | M3: 66954.94 | R3: 79083.28 | W3: 89386.28
B4: Profit Before Tax
B5: Adjustments for:
B6: Profit on Sale/Fair Value of mutual funds and AIF (Net) | C6: -2830.38 | H6: -5141.38 | M6: -547.38 | R6: -1686.78 | W6: -3856.92
B7: Depreciation, Impairment and Amortisation Expenses | C7: 36695.48 | H7: 33477.79 | M7: 24724.9 | R7: 18590.59 | W7: 17821.4
B8: Finance Costs | C8: 1327.13 | H8: 507.29 | M8: 739.14 | R8: 997.72 | W8: 933.69
B9: Interest income on Loans, Deposits & Commercial Paper | C9: -1708.09 | H9: -2777.99 | M9: -1007.51 | R9: -1253.22 | W9: -1999.64
B10: (Profit)/Loss on Sale/Disposal of Property, Plant & Equipments (Net) | C10: 138.37 | H10: -81.62 | M10: -474.19 | R10: -411.22 | W10: 18.81
B11: Dividend Income from equity investment carried at fair value through OCI | C11: 0 | H11: 0 | M11: -127.14 | R11: -127.14 | W11: -127.14
B12: Dividend Income from equity investment carried at cost | C12: 0 | H12: 0 | M12: -0.63 | R12: -0.75 | W12: -0.75
B13: Share of loss of an Associates | C13: 417.78 | H13: 1458.42 | M13: 749.7 | R13: 372.36 | W13: 1181.02
B14: Sundry balances written (back)/off (Net) | C14: -4.83 | H14: 6.11 | M14: -124.85 | R14: -210.76 | W14: -26.62
B15: Unrealised Foreign Exchange Gain (Net) | C15: -38.51 | H15: 0 | M15: 0 | R15: 0 | W15: 0
B16: Share based payments in subsidiaries | C16: -562.11 | H16: 0 | M16: 0 | R16: 63.73 | W16: 50.44
B17: Provision for doubtful trade receivables | C17: -1.47
B18: Provision for doubtful trade receivables | C18: 304 | H18: 0 | M18: -332.61 | R18: 529.03 | W18: 73.81
B19: Provision for litigation written back | C19: 395.89 | H19: 0 | M19: 0 | R19: 0 | W19: 0
B20: Profit on Fair Value of Loan | C20: 0 | H20: -53.39
B21: Profit on fair value of investment in CCPS in associate | C21: 16.88 | H21: -299.55 | M21: -3385 | R21: -42.29 | W21: 0
B22: Gain on reversal of impairment of Investments in an Associate | C22: 0 | H22: 0 | M22: 0 | R22: 0 | W22: 0
B23: Profit on fair value of investment in CCPS in associate | C23: -1090.74 | H23: -341.34 | M23: 0 | R23: 0 | W23: 0
B24: Cash Generated from operations before working capital changes | C24: 89917.78 | H24: 95554.84 | M24: 87716.18 | R24: 95904.55 | W24: 103454.38
B25: Checkline | C25: =SUM(C3:C23) -> 89951.54 | D25: =SUM(D3:D21) -> 0 | E25: =SUM(E3:E21) -> 0 | F25: =SUM(F3:F21) -> 0 | G25: =SUM(G3:G21) -> 0 | H25: =SUM(H3:H23) -> 95554.84 | I25: =SUM(I3:I21) -> 0 | J25: =SUM(J3:J21) -> 0 | K25: =SUM(K3:K21) -> 0 | L25: =SUM(L3:L21) -> 0 | M25: =SUM(M3:M21) -> 87169.37 | N25: =SUM(N3:N21) -> 0 | O25: =SUM(O3:O21) -> 0 | P25: =SUM(P3:P21) -> 0 | ... R25: =SUM(R3:R21) -> 95904.55 | S25: =SUM(S3:S24) -> 0 | T25: =SUM(T3:T24) -> 0 | U25: =SUM(U3:U24) -> 0 | V25: =SUM(V3:V24) -> 0 | W25: =SUM(W3:W21) -> 103454.38
B27: Adjustments for working capital changes :
B28: Increase/ (Decrease) in Trade Payables and Other Liabilities | C28: 4027.09 | H28: 3228.81 | M28: -2701.3 | R28: 5866.98 | W28: -521.8
B29: Decrease in Inventories | C29: -5579.91 | H29: -5590.36 | M29: 3979.05 | R29: 463.8 | W29: 1529.81
B30: Decrease/(Increase) in Trade Receivables | C30: 7330.1 | H30: -8573.94 | M30: -8812.2 | R30: -8501.43 | W30: 4213.32
B31: Decrease in Loans and Other Financial Assets | C31: 651.06 | H31: 1726.85 | M31: 5673.21 | R31: 624.14 | W31: 180.2
B32: Decrease in Other Non Financial Assets | C32: 4022.71 | H32: -8120.67 | M32: 2377.82 | R32: 729.94 | W32: 1561.32
B33: (Decrease) in Provisions | C33: 431.03 | H33: 419.39 | M33: -1640.8 | R33: -2558.09 | W33: -2351.19
B35: Cash Generated from Operations | C35: 100799.86 | H35: 78644.92 | M35: 86591.96 | R35: 92529.89 | W35: 108066.1
B36: Less | C36: 8647.03 | H36: 14259.57 | M36: 11704.37 | R36: 14629.31 | W36: 18479.76
B37: NET CASH FLOWS GENERATED FROM OPERATING ACTIVITIES* | C37: =C35-C36 -> 92152.83 | D37: =D35-D36 -> 0 | E37: =E35-E36 -> 0 | F37: =F35-F36 -> 0 | G37: =G35-G36 -> 0 | H37: =H35-H36 -> 64385.35 | I37: =I35-I36 -> 0 | J37: =J35-J36 -> 0 | ... W37: =W35-W36 -> 89586.34
B38: Checkline | C38: =C35-C36 -> 92152.83 | D38: =D35-D36 -> 0 | E38: =E35-E36 -> 0 | F38: =F35-F36 -> 0 | G38: =G35-G36 -> 0 | H38: =H35-H36 -> 64385.35 | I38: =I35-I36 -> 0 | J38: =J35-J36 -> 0 | ... W38: =W35-W36 -> 89586.34
B40: B. CASH FLOWS FROM INVESTING ACTIVITIES:
B41: Interest Received | C41: 3189.13 | H41: 2269.78 | M41: 773.83 | R41: 1177.55 | W41: 1694.43
B42: Dividend Received | C42: 0 | H42: 0 | M42: 127.14 | R42: 127.89 | W42: 127.89
B43: Purchase of Current Investments | C43: -177870 | H43: -142474.97 | M43: -204307.21 | R43: -195750 | W43: -234919.98
B44: Proceeds from Sale of Current Investments | C44: 176724.76 | H44: 148680.09 | M44: 197479.23 | R44: 192427.6 | W44: 211648.08
B45: Loans given to Body Corporate | C45: 0 | H45: 0 | M45: 0 | R45: -1500 | W45: 0
B46: Loans given to Associate | C46: 0 | H46: 0 | M46: 0 | R46: 0 | W46: -700
B47: Short term loans given | C47: -1500 | H47: 0 | M47: 0 | R47: 0 | W47: 0
B48: Proceeds from repayment of loan given | C48: 7500 | H48: 0 | M48: 0 | R48: 0 | W48: 0
B49: Purchase of Property, Plant & Equipment & Intangible Assets (Including Capital Work-in-Progress and Intangible Assets under Development) | C49: -3369.02 | H49: -48356.16 | M49: -4045.88 | R49: -4058.51 | W49: -4457.43
B50: Proceeds from Sale of Property, Plant & Equipment | C50: 165.69 | H50: 332.72 | M50: 1036.53 | R50: 1176.38 | W50: 114.36
B51: Investments in Alternative Investment Fund (AIF) | C51: 0 | H51: -185 | M51: -414.83 | R51: -580 | W51: -1002.54
B52: Proceeds from Alternative Investment Fund (AIF) | C52: 808.41 | H52: 134.5 | M52: 0 | R52: 2000.65 | W52: 1634.24
... B56: Proceeds from maturity of Deposits with Banks | C56: 33114.69 | H56: 34229.49 | M56: 7195.41 | R56: 8377.49 | W56: 24828.91
B57: NET CASH USED FLOWS IN INVESTING ACTIVITIES | C57: =SUM(C41:C56) -> -22694.91 | D57: =SUM(D41:D56) -> 0 | E57: =SUM(E41:E56) -> 0 | F57: =SUM(F41:F56) -> 0 | G57: =SUM(G41:G56) -> 0 | H57: =SUM(H41:H56) -> -23490.32 | I57: =SUM(I41:I56) -> 0 | J57: =SUM(J41:J56) -> 0 | ... W57: =SUM(W41:W56) -> -34014.39
B59: Checkline | C59: =SUM(C41:C56) -> -22694.91 | D59: =SUM(D41:D56) -> 0 | E59: =SUM(E41:E56) -> 0 | F59: =SUM(F41:F56) -> 0 | G59: =SUM(G41:G56) -> 0 | H59: =SUM(H41:H56) -> -23490.32 | I59: =SUM(I41:I56) -> 0 | J59: =SUM(J41:J56) -> 0 | ... W59: =SUM(W41:W56) -> -34014.39
B61: C. CASH FLOWS FROM FINANCING ACTIVITIES
B62: Repayment of Short Term Borrowings | C62: -17350.74 | H62: -7996.59 | M62: -23223.21 | R62: -4126.51 | W62: -11946.34
B63: Proceeds from Short Term Borrowings | C63: 18739.1 | H63: 5000 | M63: 24112.94 | R63: 2800.63 | W63: 11810.21
B64: Acquisition of Non-controlling interests | C64: 0 | H64: 0 | M64: 0 | R64: 0 | W64: -11994.82
B65: Buy Back of Shares including Transaction Costs and Taxes | C65: -22558.95 | H65: -20005.3 | M65: -99.43 | R65: -22909.7 | W65: 0
B66: Transfer (to) /from Escrow Account | C66: 5003.6 | H66: 0 | M66: -4650 | R66: 4650 | W66: -4.49
B67: Interest Paid | C67: -1326.8 | H67: -446.53 | M67: -600.31 | R67: -992.08 | W67: -924.94
B68: Dividend Paid | C68: -35561.1 | H68: -35561.1 | M68: -35292 | R68: -34920 | W68: -34920
B69: Corporate Dividend Tax paid | C69: -1908.14 | H69: 0 | M69: 0 | R69: 0 | W69: 0
B70: Payment of Principal Portion of Lease Liabilities | C70: -633.69 | H70: -712.46 | M70: -1112.57 | R70: -1333.24 | W70: -1502.21
B71: Payment against Cancellation of Share based payments in subsidiaries | C71: 0 | H71: 0 | M71: 0 | R71: 0 | W71: -253.79
B72: Cash Credit (repaid)/taken (net) (Including working capital demand loan) | C72: -13220.87 | H72: 19507.92 | M72: -19900 | R72: 533.95 | W72: -224.32
B73: NET CASH FLOWS USED IN FINANCING ACTIVITIES | C73: =SUM(C62:C72) -> -68817.59 | D73: =SUM(D62:D72) -> 0 | E73: =SUM(E62:E72) -> 0 | F73: =SUM(F62:F72) -> 0 | G73: =SUM(G62:G72) -> 0 | H73: =SUM(H62:H72) -> -40214.06 | I73: =SUM(I62:I72) -> 0 | J73: =SUM(J62:J72) -> 0 | ... W73: =SUM(W62:W72) -> -49960.7
B74: D. Effect of Foreign Exchange Fluctuation | C74: 256.87 | H74: 88.25 | M74: -1229.61 | R74: -447.13 | W74: -444.13
B75: NET INCREASE IN CASH & CASH EQUIVALENTS (A+B+C+D) | C75: =C37+C57+C73+C74 -> 897.2 | D75: =D37+D57+D73+D74 -> 0 | E75: =E37+E57+E73+E74 -> 0 | F75: =F37+F57+F73+F74 -> 0 | G75: =G37+G57+G73+G74 -> 0 | H75: =H37+H57+H73+H74 -> 769.22 | I75: =I37+I57+I73+I74 -> 0 | J75: =J37+J57+J73+J74 -> 0 | ... W75: =W37+W57+W73+W74 -> 5167.12
B76: Add-CASH & CASH EQUIVALENTS-AT THE BEGINNING OF THE YEAR | C76: 1083.94 | H76: =1981.15+6.65 -> 1987.8 | M76: =2757.29+310.69 -> 3067.98 | R76: 4678.5 | W76: 5295.39
B77: CASH & CASH EQUIVALENTS-AT THE END OF THE YEAR | C77: =C75+C76 -> 1981.14 | D77: =D75+D76 -> 0 | E77: =E75+E76 -> 0 | F77: =F75+F76 -> 0 | G77: =G75+G76 -> 0 | H77: =H75+H76 -> 2757.02 | I77: =I75+I76 -> 0 | J77: =J75+J76 -> 0 | ... W77: =W75+W76 -> 10462.51
B78: Checkline | C78: =C75+C76 -> 1981.14 | D78: =D75+D76 -> 0 | E78: =E75+E76 -> 0 | F78: =F75+F76 -> 0 | G78: =G75+G76 -> 0 | H78: =H75+H76 -> 2757.02 | I78: =I75+I76 -> 0 | J78: =J75+J76 -> 0 | ... Z78: =Z75+Z76 -> 0
B79: Cash & Cash Equivalents includes:
B80: Balances with banks | C80: 1395.16 | H80: 2507.83 | M80: 2849.29 | R80: 4060.39 | W80: 8288.37
B81: Fixed Deposits with Banks (Original Maturity of less than 3 Months) | C81: 0 | H81: 51.62 | M81: 1766.85 | R81: 1180.31 | W81: 2000
B82: Cheques in hand | C82: 561.21 | H82: 176.8 | M82: 0.17 | R82: 0 | W82: 21.46
B83: Fund in transit | C83: 0 | H83: 0 | M83: 42.26 | R83: 29.56 | W83: 111.21
B84: Cash on hand | C84: 24.78 | H84: 21.04 | M84: 19.93 | R84: 25.13 | W84: 41.47
B85: Total Cash & Cash Equivalents (Refer Note No. : 3.13) | C85: =SUM(C80:C84) -> 1981.15 | D85: =SUM(D80:D84) -> 0 | E85: =SUM(E80:E84) -> 0 | F85: =SUM(F80:F84) -> 0 | G85: =SUM(G80:G84) -> 0 | H85: =SUM(H80:H84) -> 2757.29 | I85: =SUM(I80:I84) -> 0 | J85: =SUM(J80:J84) -> 0 | ... W85: =SUM(W80:W84) -> 10462.51
B86: Checkline | C86: =SUM(C80:C84) -> 1981.15 | D86: =SUM(D80:D84) -> 0 | E86: =SUM(E80:E84) -> 0 | F86: =SUM(F80:F84) -> 0 | G86: =SUM(G80:G84) -> 0 | H86: =SUM(H80:H84) -> 2757.29 | I86: =SUM(I80:I84) -> 0 | J86: =SUM(J80:J84) -> 0 | ... Z86: =SUM(Z80:Z84) -> 0

Sheet Revenue Tab
B1: FY Mar Rs. Lakhs | C1: FY 2020-21 | D1: Q1 2021-22 | E1: Q2 2021-22 | F1: Q3 2021-22 | G1: Q4 2021-22 | H1: FY 2021-22 | I1: Q1 2022-23 | J1: Q2 2022-23 | K1: Q3 2022-23 | L1: Q4 2022-23 | M1: FY 2022-23 | N1: Q1 2023-24 | O1: Q2 2023-24 | P1: Q3 2023-24 | Q1: Q4 2023-24 | R1: FY 2023-24 | S1: Q1 2024-25 | T1: Q2 2024-25 | U1: Q3 2024-25 | V1: Q4 2024-25 | W1: FY 2024-25 | X1: Q1 2025-26 | Y1: E Q2 2025-26 | Z1: E Q3 2025-26 | AA1: E Q4 2025-26 | AB1: E FY 2025-26 | AC1: E FY 2026-27 | AD1: E FY 2027-28 | AE1: E FY 2028-29 | AF1: FY 2029-30
B2: ='[1]Income Statement'!B6 -> Total revenue from operations | C2: ='Income Statement'!C5 -> 295080 | D2: ='Income Statement'!D5 -> 67167 | E2: ='Income Statement'!E5 -> 82645 | F2: ='Income Statement'!F5 -> 98848 | G2: ='Income Statement'!G5 -> 80068 | H2: ='Income Statement'!H5 -> 328728 | I2: ='Income Statement'!I5 -> 77964 | J2: ='Income Statement'!J5 -> 85574 | ... X2: ='Income Statement'!X5 -> 92568 | Y2: =T2*(1+Y3) -> 96323.04 | Z2: =U2*(1+Z3) -> 112401.7 | AA2: =V2*(1+AA3) -> 103932.58 | AB2: =SUM(X2:AA2) -> 405225.31 | AC2: =AB2*(1+AC3) -> 427917.93 | AD2: =AC2*(1+AD3) -> 451881.33 | AE2: =AD2*(1+AE3) -> 477186.69 | AF2: =AE2*(1+AF3) -> 503909.14
B3: ='[1]Income Statement'!B7 -> Y0Y | H3: ='Income Statement'!H6 -> 0.11403009 | I3: =I2/D2-1 -> 0.16074858 | J3: =J2/E2-1 -> 0.035440741 | K3: =K2/F2-1 -> 0.0011128197 | L3: =L2/G2-1 -> 0.06122296 | M3: ='Income Statement'!M6 -> 0.057001533 | N3: =N2/I2-1 -> 0.06964753 | O3: =O2/J2-1 -> 0.023652044 | P3: =P2/K2-1 -> 0.023696922 | Q3: =Q2/L2-1 -> 0.061480523 | R3: ='Income Statement'!R6 -> 0.043235885 | S3: =S2/N2-1 -> 0.099035902 | T3: =T2/O2-1 -> 0.041290897 | U3: =U2/P2-1 -> 0.05071913 | V3: =V2/Q2-1 -> 0.091214493 | W3: ='Income Statement'!W6 -> 0.069632458 | X3: =X2/S2-1 -> 0.0099833066 | Y3: =CHOOSE(Y4,Y5,Y6,Y7) -> 0.056 | Z3: =CHOOSE($Y$4,Z5,Z6,Z7) -> 0.056 | AA3: =CHOOSE($Y$4,AA5,AA6,AA7) -> 0.056 | AB3: =AB2/W2-1 -> 0.04512241 | AC3: =CHOOSE($Y$4,AC5,AC6,AC7) -> 0.056 | AD3: =CHOOSE($Y$4,AD5,AD6,AD7) -> 0.056 | AE3: =CHOOSE($Y$4,AE5,AE6,AE7) -> 0.056 | AF3: =CHOOSE($Y$4,AF5,AF6,AF7) -> 0.056
B4: Index | Y4: 2
B5: Low | Y5: 0.025 | Z5: 0.025 | AA5: 0.025 | AC5: 0.025 | AD5: 0.025 | AE5: 0.025 | AF5: 0.025
B6: Mid | Y6: 0.056 | Z6: 0.056 | AA6: 0.056 | AC6: 0.056 | AD6: 0.056 | AE6: 0.056 | AF6: 0.056
B7: High | Y7: 0.095 | Z7: 0.095 | AA7: 0.095 | AC7: 0.095 | AD7: 0.095 | AE7: 0.095 | AF7: 0.095
B9: ='[1]Income Statement'!B9 -> Other income | C9: ='Income Statement'!C4 -> 7027 | D9: ='Income Statement'!D4 -> 1072 | E9: ='Income Statement'!E4 -> 3761 | F9: ='Income Statement'!F4 -> 1663 | G9: ='Income Statement'!G4 -> 3029 | H9: ='Income Statement'!H4 -> 9525 | I9: ='Income Statement'!I4 -> 633 | J9: ='Income Statement'!J4 -> 4199 | ... X9: ='Income Statement'!X4 -> 2159 | Y9: =Y2*Y10 -> 1926.4608 | Z9: =Z2*Z10 -> 2248.0339 | AA9: =AA2*AA10 -> 2078.6515 | AB9: =SUM(X9:AA9) -> 8412.1462 | AC9: =AC2*AC10 -> 8558.3586 | AD9: =AD2*AD10 -> 9037.6267 | AE9: =AE2*AE10 -> 9543.7338 | AF9: =AF2*AF10 -> 10078.183
B10: % of Total revenue from Operation | C10: =C9/C2 -> 0.023813881 | D10: =D9/D2 -> 0.015960219 | E10: =E9/E2 -> 0.045507895 | F10: =F9/F2 -> 0.01682381 | G10: =G9/G2 -> 0.037830344 | H10: =H9/H2 -> 0.028975323 | I10: =I9/I2 -> 0.0081191319 | J10: =J9/J2 -> 0.049068642 | ... X10: =X9/X2 -> 0.023323395 | Y10: 0.02 | Z10: 0.02 | AA10: 0.02 | AC10: 0.02 | AD10: 0.02 | AE10: 0.02 | AF10: 0.02
B11: ='[1]Income Statement'!B10 -> Total Revenue | C11: ='Income Statement'!C5 -> 295080 | D11: ='Income Statement'!D5 -> 67167 | E11: ='Income Statement'!E5 -> 82645 | F11: ='Income Statement'!F5 -> 98848 | G11: ='Income Statement'!G5 -> 80068 | H11: ='Income Statement'!H5 -> 328728 | I11: ='Income Statement'!I5 -> 77964 | J11: ='Income Statement'!J5 -> 85574 | ... X11: ='Income Statement'!X5 -> 92568 | Y11: =Y2+Y9 -> 98249.501 | Z11: =Z2+Z9 -> 114649.73 | AA11: =AA2+AA9 -> 106011.23 | AB11: =AB2+AB9 -> 413637.46 | AC11: =AC2+AC9 -> 436476.29 | AD11: =AD2+AD9 -> 460918.96 | AE11: =AE2+AE9 -> 486730.42 | AF11: =AF2+AF9 -> 513987.33
B12: ='Income Statement'!B6 -> YOY | C12: ='Income Statement'!C6 -> 0 | D12: ='Income Statement'!D6 -> 0 | E12: ='Income Statement'!E6 -> 0 | F12: ='Income Statement'!F6 -> 0 | G12: ='Income Statement'!G6 -> 0 | H12: ='Income Statement'!H6 -> 0.11403009 | I12: ='Income Statement'!I6 -> 0.16074858 | ... X12: ='Income Statement'!X6 -> 0.0099833066 | Y12: =Y11/S11-1 -> 0.071972557 | Z12: =Z11/T11-1 -> 0.2569175 | AA12: =AA11/U11-1 -> -0.0040376592 | AB12: =AB11/W11-1 -> 0.066818297 | AC12: =AC11/AB11-1 -> 0.055214607 | AD12: =AD11/AC11-1 -> 0.056 | AE12: =AE11/AD11-1 -> 0.056 | AF12: =AF11/AE11-1 -> 0.056

Sheet Expense Tab
B1: FY Mar Rs. Lakhs | C1: FY 2020-21 | D1: Q1 2021-22 | E1: Q2 2021-22 | F1: Q3 2021-22 | G1: Q4 2021-22 | H1: FY 2021-22 | I1: Q1 2022-23 | J1: Q2 2022-23 | K1: Q3 2022-23 | L1: Q4 2022-23 | M1: FY 2022-23 | N1: Q1 2023-24 | O1: Q2 2023-24 | P1: Q3 2023-24 | Q1: Q4 2023-24 | R1: FY 2023-24 | S1: Q1 2024-25 | T1: Q2 2024-25 | U1: Q3 2024-25 | V1: Q4 2024-25 | W1: FY 2024-25 | X1: Q1 2025-26 | Y1: E Q2 2025-26 | Z1: E Q3 2025-26 | AA1: E Q4 2025-26 | AB1: E FY 2025-26 | AC1: E FY 2026-27 | AD1: E FY 2027-28 | AE1: E FY 2028-29 | AF1: FY 2029-30
B2: ='[1]Income Statement'!B15 -> Cost of materials consumed | C2: ='Income Statement'!C10 -> 70855 | D2: ='Income Statement'!D10 -> 18394 | E2: ='Income Statement'!E10 -> 24793 | F2: ='Income Statement'!F10 -> 24356 | G2: ='Income Statement'!G10 -> 22487 | H2: ='Income Statement'!H10 -> 90030 | I2: ='Income Statement'!I10 -> 16342 | J2: ='Income Statement'!J10 -> 24765 | ... X2: ='Income Statement'!X10 -> 16356 | Y2: =Y3*Y9 -> 18294.057 | Z2: =Z3*Z9 -> 21347.78 | AA2: =AA3*AA9 -> 19739.291 | AB2: =X2+Y2+Z2+AA2 -> 75737.127 | AC2: =AC3*AC9 -> 81271.885 | AD2: =AD3*AD9 -> 85823.11 | AE2: =AE3*AE9 -> 90629.205 | AF2: =AF3*AF9 -> 95704.44
B3: % of COGS | C3: =C2/C9 -> 0.51071452 | D3: =D2/D9 -> 0.54992825 | E3: =E2/E9 -> 0.7049474 | F3: =F2/F9 -> 0.51249895 | G3: =G2/G9 -> 0.51181264 | H3: =H2/H9 -> 0.56241332 | I3: =I2/I9 -> 0.38238529 | J3: =J2/J9 -> 0.59956422 | ... X3: =X2/X9 -> 0.3585191 | Y3: 0.38 | Z3: 0.38 | AA3: 0.38 | AC3: 0.38 | AD3: 0.38 | AE3: 0.38 | AF3: 0.38
B4: ='[1]Income Statement'!B16 -> Purchase of stock-in-trade | C4: ='Income Statement'!C11 -> 24009 | D4: ='Income Statement'!D11 -> 4331 | E4: ='Income Statement'!E11 -> 2754 | F4: ='Income Statement'!F11 -> 4800 | G4: ='Income Statement'!G11 -> 10462 | H4: ='Income Statement'!H11 -> 22347 | I4: ='Income Statement'!I11 -> 6585 | J4: ='Income Statement'!J11 -> 7536 | ... X4: ='Income Statement'!X11 -> 10857 | Y4: =Y5*Y9 -> 9628.4511 | Z4: =Z5*Z9 -> 11235.674 | AA4: =AA5*AA9 -> 10389.1 | AB4: =X4+Y4+Z4+AA4 -> 42110.225 | AC4: =AC5*AC9 -> 42774.676 | AD4: =AD5*AD9 -> 45170.058 | AE4: =AE5*AE9 -> 47699.581 | AF4: =AF5*AF9 -> 50370.758
B5: % of COGS | C5: =C4/C9 -> 0.17305405 | D5: =D4/D9 -> 0.12948457 | E5: =E4/E9 -> 0.078305374 | F5: =F4/F9 -> 0.1010016 | G5: =G4/G9 -> 0.23811908 | H5: =H4/H9 -> 0.13960069 | I5: =I4/I9 -> 0.15408194 | J5: =J4/J9 -> 0.18244765 | ... X5: =X4/X9 -> 0.23798251 | Y5: 0.2 | Z5: 0.2 | AA5: 0.2 | AC5: 0.2 | AD5: 0.2 | AE5: 0.2 | AF5: 0.2
B6: ='Income Statement'!B12 -> (Increase)/Decrease in Inventories of Finished Goods, Stock in Trade and Work-in-Progress | C6: ='Income Statement'!C12 -> -1940 | D6: ='Income Statement'!D12 -> -263 | E6: ='Income Statement'!E12 -> -2909 | F6: ='Income Statement'!F12 -> 2543 | G6: ='Income Statement'!G12 -> -3960 | H6: ='Income Statement'!H12 -> -4589 | I6: ='Income Statement'!I12 -> 6180 | ... X6: ='Income Statement'!X12 -> 433 | Y6: =Y9-Y4-Y2 -> 20219.747 | Z6: =Z9-Z4-Z2 -> 23594.914 | AA6: =AA9-AA4-AA2 -> 21817.111 | AB6: =X6+Y6+Z6+AA6 -> 66064.772 | AC6: =AC9-AC4-AC2 -> 89826.82 | AD6: =AD9-AD4-AD2 -> 94857.122 | AE6: =AE9-AE4-AE2 -> 100169.12 | AF6: =AF9-AF4-AF2 -> 105778.59
B7: ='Income Statement'!B13 -> advertisment and sale | C7: ='Income Statement'!C13 -> 45813 | D7: ='Income Statement'!D13 -> 10986 | E7: ='Income Statement'!E13 -> 10532 | F7: ='Income Statement'!F13 -> 15825 | G7: ='Income Statement'!G13 -> 14947 | H7: ='Income Statement'!H13 -> 52290 | I7: ='Income Statement'!I13 -> 13630 | ... X7: ='Income Statement'!X13 -> 17975 | Y7: =Y8*Y9 -> 16368.367 | Z7: =Z8*Z9 -> 19100.645 | AA7: =AA8*AA9 -> 17661.471 | AB7: =X7+Y7+Z7+AA7 -> 71105.482 | AC7: =AC8*AC9 -> 72716.95 | AD7: =AD8*AD9 -> 76789.099 | AE7: =AE8*AE9 -> 81089.288 | AF7: =AF8*AF9 -> 85630.288
B8: % of COGS | C8: =C7/C9 -> 0.33021472 | D8: =D7/D9 -> 0.32845013 | E8: =E7/E9 -> 0.29945977 | F8: =F7/F9 -> 0.33298965 | G8: =G7/G9 -> 0.34019938 | H8: =H7/H9 -> 0.32665326 | I8: =I7/I9 -> 0.31892739 | J8: =J7/J9 -> 0.34252512 | ... X8: =X7/X9 -> 0.39400715 | Y8: 0.34 | Z8: 0.34 | AA8: 0.34 | AC8: 0.34 | AD8: 0.34 | AE8: 0.34 | AF8: 0.34
B9: ='[1]Income Statement'!B18 -> COGS | C9: ='Income Statement'!C14 -> 138737 | D9: ='Income Statement'!D14 -> 33448 | E9: ='Income Statement'!E14 -> 35170 | F9: ='Income Statement'!F14 -> 47524 | G9: ='Income Statement'!G14 -> 43936 | H9: ='Income Statement'!H14 -> 160078 | I9: ='Income Statement'!I14 -> 42737 | J9: ='Income Statement'!J14 -> 41305 | ... X9: ='Income Statement'!X14 -> 45621 | Y9: =Y10*Y17 -> 48142.255 | Z9: =Z10*Z17 -> 56178.368 | AA9: =AA10*AA17 -> 51945.501 | AB9: =X9+Y9+Z9+AA9 -> 201887.12 | AC9: =AC10*AC17 -> 213873.38 | AD9: =AD10*AD17 -> 225850.29 | AE9: =AE10*AE17 -> 238497.91 | AF9: =AF10*AF17 -> 251853.79
B10: % Total revenue from operation | C10: =C9/C17 -> 0.47016741 | D10: =D9/D17 -> 0.49798264 | E10: =E9/E17 -> 0.42555509 | F10: =F9/F17 -> 0.48077857 | G10: =G9/G17 -> 0.54873358 | H10: =H9/H17 -> 0.48696187 | I10: =I9/I17 -> 0.54816325 | J10: =J9/J17 -> 0.48268166 | ... X10: =X9/X17 -> 0.4928377 | Y10: 0.49 | Z10: 0.49 | AA10: 0.49 | AC10: 0.49 | AD10: 0.49 | AE10: 0.49 | AF10: 0.49
B11: ='[1]Income Statement'!B22 -> Employee benefits expense | C11: ='Income Statement'!C18 -> 30917 | D11: ='Income Statement'!D18 -> 8450 | E11: ='Income Statement'!E18 -> 8207 | F11: ='Income Statement'!F18 -> 7235 | G11: ='Income Statement'!G18 -> 7885 | H11: ='Income Statement'!H18 -> 31777 | I11: ='Income Statement'!I18 -> 8879 | J11: ='Income Statement'!J18 -> 9347 | ... X11: ='Income Statement'!X18 -> 11946 | Y11: =Y12*Y15 -> 10807.445 | Z11: =Z12*Z15 -> 12611.47 | AA11: =AA12*AA15 -> 11661.235 | AB11: =X11+Y11+Z11+AA11 -> 47026.15 | AC11: =AC12*AC15 -> 48012.392 | AD11: =AD12*AD15 -> 50701.086 | AE11: =AE12*AE15 -> 53540.346 | AF11: =AF12*AF15 -> 56538.606
B12: % of Operating Exp | C12: =C11/C15 -> 0.50674469 | D12: =D11/D15 -> 0.53904057 | E12: =E11/E15 -> 0.51306577 | F12: =F11/F15 -> 0.46656349 | G12: =G11/G15 -> 0.47190137 | H12: =H11/H15 -> 0.49738605 | I12: =I11/I15 -> 0.49994369 | J12: =J11/J15 -> 0.4552406 | ... X12: =X11/X15 -> 0.51125567 | Y12: 0.5 | Z12: 0.5 | AA12: 0.5 | AC12: 0.5 | AD12: 0.5 | AE12: 0.5 | AF12: 0.5
B13: ='[1]Income Statement'!B24 -> Other expenses | C13: ='Income Statement'!C19 -> 30094 | D13: ='Income Statement'!D19 -> 7226 | E13: ='Income Statement'!E19 -> 7789 | F13: ='Income Statement'!F19 -> 8272 | G13: ='Income Statement'!G19 -> 8824 | H13: ='Income Statement'!H19 -> 32111 | I13: ='Income Statement'!I19 -> 8881 | J13: ='Income Statement'!J19 -> 11185 | ... X13: ='Income Statement'!X19 -> 11420 | Y13: =Y14*Y15 -> 10375.147 | Z13: =Z14*Z15 -> 12107.011 | AA13: =AA14*AA15 -> 11194.786 | AB13: =X13+Y13+Z13+AA13 -> 45096.944 | AC13: =AC14*AC15 -> 46091.896 | AD13: =AD14*AD15 -> 48673.042 | AE13: =AE14*AE15 -> 51398.733 | AF13: =AF14*AF15 -> 54277.062
B14: % of Operating Exp | C14: =C13/C15 -> 0.49325531 | D14: =D13/D15 -> 0.46095943 | E14: =E13/E15 -> 0.48693423 | F14: =F13/F15 -> 0.53343651 | G14: =G13/G15 -> 0.52809863 | H14: =H13/H15 -> 0.50261395 | I14: =I13/I15 -> 0.50005631 | J14: =J13/J15 -> 0.5447594 | ... X14: =X13/X15 -> 0.48874433 | Y14: 0.48 | Z14: 0.48 | AA14: 0.48 | AC14: 0.48 | AD14: 0.48 | AE14: 0.48 | AF14: 0.48
B15: ='Income Statement'!B20 -> Operating Expenses | C15: ='Income Statement'!C20 -> 61011 | D15: ='Income Statement'!D20 -> 15676 | E15: ='Income Statement'!E20 -> 15996 | F15: ='Income Statement'!F20 -> 15507 | G15: ='Income Statement'!G20 -> 16709 | H15: ='Income Statement'!H20 -> 63888 | I15: ='Income Statement'!I20 -> 17760 | ... X15: ='Income Statement'!X20 -> 23366 | Y15: =Y16*Y17 -> 21614.89 | Z15: =Z16*Z17 -> 25222.941 | AA15: =AA16*AA17 -> 23322.47 | AB15: =X15+Y15+Z15+AA15 -> 93526.301 | AC15: =AC16*AC17 -> 96024.783 | AD15: =AD16*AD17 -> 101402.17 | AE15: =AE16*AE17 -> 107080.69 | AF15: =AF16*AF17 -> 113077.21
B16: % of Revenue from Operation | C16: =C15/C17 -> 0.20676088 | D16: =D15/D17 -> 0.23338842 | E16: =E15/E17 -> 0.19355073 | F16: =F15/F17 -> 0.15687723 | G16: =G15/G17 -> 0.20868512 | H16: =H15/H17 -> 0.19434913 | I16: =I15/I17 -> 0.22779744 | J16: =J15/J17 -> 0.23993269 | ... X16: =X15/X17 -> 0.25241984 | Y16: 0.22 | Z16: 0.22 | AA16: 0.22 | AC16: 0.22 | AD16: 0.22 | AE16: 0.22 | AF16: 0.22
B17: ='[1]Income Statement'!B6 -> Total revenue from operations | C17: ='Income Statement'!C5 -> 295080 | D17: ='Income Statement'!D5 -> 67167 | E17: ='Income Statement'!E5 -> 82645 | F17: ='Income Statement'!F5 -> 98848 | G17: ='Income Statement'!G5 -> 80068 | H17: ='Income Statement'!H5 -> 328728 | I17: ='Income Statement'!I5 -> 77964 | J17: ='Income Statement'!J5 -> 85574 | ... AA17: ='Income Statement'!AA5 -> 106011.23 | AB17: =X17+Y17+Z17+AA17 -> 411478.46 | AC17: ='Income Statement'!AC5 -> 436476.29 | AD17: ='Income Statement'!AD5 -> 460918.96 | AE17: ='Income Statement'!AE5 -> 486730.42 | AF17: ='Income Statement'!AF5 -> 513987.33

Sheet Current Assets
B1: FY Mar Rs. Lakhs | C1: FY 2020-21 | D1: Q1 2021-22 | E1: Q2 2021-22 | F1: Q3 2021-22 | G1: Q4 2021-22 | H1: FY 2021-22 | I1: Q1 2022-23 | J1: Q2 2022-23 | K1: Q3 2022-23 | L1: Q4 2022-23 | M1: FY 2022-23 | N1: Q1 2023-24 | O1: Q2 2023-24 | P1: Q3 2023-24 | Q1: Q4 2023-24 | R1: FY 2023-24 | S1: Q1 2024-25 | T1: Q2 2024-25 | U1: Q3 2024-25 | V1: Q4 2024-25 | W1: FY 2024-25 | X1: Q1 2025-26 | Y1: E Q2 2025-26 | Z1: E Q3 2025-26 | AA1: E Q4 2025-26 | AB1: E FY 2025-26 | AC1: E FY 2026-27 | AD1: E FY 2027-28 | AE1: E FY 2028-29 | AF1: FY 2029-30
B2: Inventories | C2: ='Balance Sheet'!C20 -> 30044.65 | D2: ='Balance Sheet'!D20 -> 0 | E2: ='Balance Sheet'!E20 -> 0 | F2: ='Balance Sheet'!F20 -> 0 | G2: ='Balance Sheet'!G20 -> 0 | H2: ='Balance Sheet'!H20 -> 35761.43 | I2: ='Balance Sheet'!I20 -> 0 | J2: ='Balance Sheet'!J20 -> 0 | ... AA2: ='Balance Sheet'!AA20 -> 0 | AB2: =AB20*AB16/365 -> 37584.935 | AC2: =AC20*AC16/365 -> 39844.904 | AD2: =AD20*AD16/365 -> 42076.219 | AE2: =AE20*AE16/365 -> 44432.487 | AF2: =AF20*AF16/365 -> 46920.706
B3: Financial assets
B4: Investments | C4: ='Balance Sheet'!C22 -> 8890.65 | D4: ='Balance Sheet'!D22 -> 0 | E4: ='Balance Sheet'!E22 -> 0 | F4: ='Balance Sheet'!F22 -> 0 | G4: ='Balance Sheet'!G22 -> 0 | H4: ='Balance Sheet'!H22 -> 3951.69 | I4: ='Balance Sheet'!I22 -> 0 | J4: ='Balance Sheet'!J22 -> 0 | ... AA4: ='Balance Sheet'!AA22 -> 0 | AB4: =AB5*AB18 -> 29442.512 | AC4: =AC5*AC18 -> 29954.255 | AD4: =AD5*AD18 -> 31631.693 | AE4: =AE5*AE18 -> 33403.068 | AF4: =AF5*AF18 -> 35273.64
B5: % of Other Income | C5: =C4/C18 -> 1.2652128 | D5: =D4/D18 -> 0 | E5: =E4/E18 -> 0 | F5: =F4/F18 -> 0 | G5: =G4/G18 -> 0 | H5: =H4/H18 -> 0.41487559 | I5: =I4/I18 -> 0 | J5: =J4/J18 -> 0 | ... AA5: =AA4/AA18 -> 0 | AB5: 3.5 | AC5: 3.5 | AD5: 3.5 | AE5: 3.5 | AF5: 3.5
B6: Trade receivables | C6: ='Balance Sheet'!C23 -> 23175.31 | D6: ='Balance Sheet'!D23 -> 0 | E6: ='Balance Sheet'!E23 -> 0 | F6: ='Balance Sheet'!F23 -> 0 | G6: ='Balance Sheet'!G23 -> 0 | H6: ='Balance Sheet'!H23 -> 32091.87 | I6: ='Balance Sheet'!I23 -> 0 | J6: ='Balance Sheet'!J23 -> 0 | ... AA6: ='Balance Sheet'!AA23 -> 0 | AB6: =AB21*AB17/365 -> 50996.399 | AC6: =AC21*AC17/365 -> 53812.145 | AD6: =AD21*AD17/365 -> 56825.625 | AE6: =AE21*AE17/365 -> 60007.86 | AF6: =AF21*AF17/365 -> 63368.3
B7: Other bank balances | C7: ='Balance Sheet'!C25 -> 34056.15 | D7: ='Balance Sheet'!D25 -> 0 | E7: ='Balance Sheet'!E25 -> 0 | F7: ='Balance Sheet'!F25 -> 0 | G7: ='Balance Sheet'!G25 -> 0 | H7: ='Balance Sheet'!H25 -> 8843.07 | I7: ='Balance Sheet'!I25 -> 0 | J7: ='Balance Sheet'!J25 -> 0 | ... AA7: ='Balance Sheet'!AA25 -> 0 | AB7: =AB8*AB17 -> 20681.873 | AC7: =AC8*AC17 -> 21823.814 | AD7: =AD8*AD17 -> 23045.948 | AE7: =AE8*AE17 -> 24336.521 | AF7: =AF8*AF17 -> 25699.366
B8: % of revenue from Operation | C8: =C7/C17 -> 0.11541328 | D8: =D7/D17 -> 0 | E8: =E7/E17 -> 0 | F8: =F7/F17 -> 0 | G8: =G7/G17 -> 0 | H8: =H7/H17 -> 0.026900872 | I8: =I7/I17 -> 0 | J8: =J7/J17 -> 0 | ... AA8: =AA7/AA17 -> 0 | AB8: 0.05 | AC8: 0.05 | AD8: 0.05 | AE8: 0.05 | AF8: 0.05
B9: Other financial assets | C9: ='Balance Sheet'!C27 -> 3625.45 | D9: ='Balance Sheet'!D27 -> 0 | E9: ='Balance Sheet'!E27 -> 0 | F9: ='Balance Sheet'!F27 -> 0 | G9: ='Balance Sheet'!G27 -> 0 | H9: ='Balance Sheet'!H27 -> 4567.9 | I9: ='Balance Sheet'!I27 -> 0 | J9: ='Balance Sheet'!J27 -> 0 | ... AA9: ='Balance Sheet'!AA27 -> 0 | AB9: =AB10*AB17 -> 12409.124 | AC9: =AC10*AC17 -> 13094.289 | AD9: =AD10*AD17 -> 13827.569 | AE9: =AE10*AE17 -> 14601.913 | AF9: =AF10*AF17 -> 15419.62
B10: % of revenue from Operation | C10: =C9/C17 -> 0.012286329 | D10: =D9/D17 -> 0 | E10: =E9/E17 -> 0 | F10: =F9/F17 -> 0 | G10: =G9/G17 -> 0 | H10: =H9/H17 -> 0.013895683 | I10: =I9/I17 -> 0 | J10: =J9/J17 -> 0 | ... AA10: =AA9/AA17 -> 0 | AB10: 0.03 | AC10: 0.03 | AD10: 0.03 | AE10: 0.03 | AF10: 0.03
B11: Other current assets | C11: ='Balance Sheet'!C29 -> 10602.75 | D11: ='Balance Sheet'!D29 -> 0 | E11: ='Balance Sheet'!E29 -> 0 | F11: ='Balance Sheet'!F29 -> 0 | G11: ='Balance Sheet'!G29 -> 0 | H11: ='Balance Sheet'!H29 -> 18841.03 | I11: ='Balance Sheet'!I29 -> 0 | J11: ='Balance Sheet'!J29 -> 0 | ... AA11: ='Balance Sheet'!AA29 -> 0 | AB11: =AB12*AB17 -> 16545.498 | AC11: =AC12*AC17 -> 17459.052 | AD11: =AD12*AD17 -> 18436.758 | AE11: =AE12*AE17 -> 19469.217 | AF11: =AF12*AF17 -> 20559.493
B12: % of revenue from Operation | C12: =C11/C17 -> 0.035931781 | D12: =D11/D17 -> 0 | E12: =E11/E17 -> 0 | F12: =F11/F17 -> 0 | G12: =G11/G17 -> 0 | H12: =H11/H17 -> 0.057314953 | I12: =I11/I17 -> 0 | J12: =J11/J17 -> 0 | ... AA12: =AA11/AA17 -> 0 | AB12: 0.04 | AC12: 0.04 | AD12: 0.04 | AE12: 0.04 | AF12: 0.04
B14: Current Assets (Ex. Cash & Financial Derivatives) | C14: =C11+C9+C7+C6+C4+C2 -> 110394.96 | D14: =D11+D9+D7+D6+D4+D2 -> 0 | E14: =E11+E9+E7+E6+E4+E2 -> 0 | F14: =F11+F9+F7+F6+F4+F2 -> 0 | G14: =G11+G9+G7+G6+G4+G2 -> 0 | H14: =H11+H9+H7+H6+H4+H2 -> 104056.99 | I14: =I11+I9+I7+I6+I4+I2 -> 0 | J14: =J11+J9+J7+J6+J4+J2 -> 0 | ... AF14: =AF11+AF9+AF7+AF6+AF4+AF2 -> 207241.13
B16: COGS | C16: ='Income Statement'!C14 -> 138737 | D16: ='Income Statement'!D14 -> 33448 | E16: ='Income Statement'!E14 -> 35170 | F16: ='Income Statement'!F14 -> 47524 | G16: ='Income Statement'!G14 -> 43936 | H16: ='Income Statement'!H14 -> 160078 | I16: ='Income Statement'!I14 -> 42737 | J16: ='Income Statement'!J14 -> 41305 | ... AF16: ='Income Statement'!AF14 -> 251853.79
B17: Total revenue from operations | C17: ='Income Statement'!C5 -> 295080 | D17: ='Income Statement'!D5 -> 67167 | E17: ='Income Statement'!E5 -> 82645 | F17: ='Income Statement'!F5 -> 98848 | G17: ='Income Statement'!G5 -> 80068 | H17: ='Income Statement'!H5 -> 328728 | I17: ='Income Statement'!I5 -> 77964 | J17: ='Income Statement'!J5 -> 85574 | ... AF17: ='Income Statement'!AF5 -> 513987.33
B18: Other income | C18: ='Income Statement'!C4 -> 7027 | D18: ='Income Statement'!D4 -> 1072 | E18: ='Income Statement'!E4 -> 3761 | F18: ='Income Statement'!F4 -> 1663 | G18: ='Income Statement'!G4 -> 3029 | H18: ='Income Statement'!H4 -> 9525 | I18: ='Income Statement'!I4 -> 633 | J18: ='Income Statement'!J4 -> 4199 | ... AF18: ='Income Statement'!AF4 -> 10078.183
B20: Inventory Days | C20: =C2/C16*365 -> 79.043782 | D20: =D2/D16*365 -> 0 | E20: =E2/E16*365 -> 0 | F20: =F2/F16*365 -> 0 | G20: =G2/G16*365 -> 0 | H20: =H2/H16*365 -> 81.541011 | I20: =I2/I16*365 -> 0 | J20: =J2/J16*365 -> 0 | ... AA20: =AA2/AA16*365 -> 0 | AB20: =(M20*365)/(2*M16)*(2*M16)/365 -> 67.951344 | AC20: 68 | AD20: 68 | AE20: 68 | AF20: 68
B21: Receivable Days | C21: =C6/C17*365 -> 28.666762 | D21: =D6/D17*365 -> 0 | E21: =E6/E17*365 -> 0 | F21: =F6/F17*365 -> 0 | G21: =G6/G17*365 -> 0 | H21: =H6/H17*365 -> 35.632902 | I21: =I6/I17*365 -> 0 | J21: =J6/J17*365 -> 0 | ... AA21: =AA6/AA17*365 -> 0 | AB21: 45 | AC21: 45 | AD21: 45 | AE21: 45 | AF21: 45
AB27: [ Inventory Days - (Io*365)/(2*COGS)]* (2*COGS)/365

Sheet Current Liability
B1: FY Mar Rs. Lakhs | C1: FY 2020-21 | D1: Q1 2021-22 | E1: Q2 2021-22 | F1: Q3 2021-22 | G1: Q4 2021-22 | H1: FY 2021-22 | I1: Q1 2022-23 | J1: Q2 2022-23 | K1: Q3 2022-23 | L1: Q4 2022-23 | M1: FY 2022-23 | N1: Q1 2023-24 | O1: Q2 2023-24 | P1: Q3 2023-24 | Q1: Q4 2023-24 | R1: FY 2023-24 | S1: Q1 2024-25 | T1: Q2 2024-25 | U1: Q3 2024-25 | V1: Q4 2024-25 | W1: FY 2024-25 | X1: Q1 2025-26 | Y1: E Q2 2025-26 | Z1: E Q3 2025-26 | AA1: E Q4 2025-26 | AB1: E FY 2025-26 | AC1: E FY 2026-27 | AD1: E FY 2027-28 | AE1: E FY 2028-29 | AF1: FY 2029-30
B2: Financial liabilities
B3: Lease liabilities | C3: ='Balance Sheet'!C54 -> 463.33 | D3: ='Balance Sheet'!D54 -> 0 | E3: ='Balance Sheet'!E54 -> 0 | F3: ='Balance Sheet'!F54 -> 0 | G3: ='Balance Sheet'!G54 -> 0 | H3: ='Balance Sheet'!H54 -> 796.06 | I3: ='Balance Sheet'!I54 -> 0 | J3: ='Balance Sheet'!J54 -> 0 | ... AA3: ='Balance Sheet'!AA54 -> 0 | AB3: =AB4*AB19 -> 1090.1905 | AC3: =AC4*AC19 -> 1154.9163 | AD3: =AD4*AD19 -> 1219.5916 | AE3: =AE4*AE19 -> 1287.8887 | AF3: =AF4*AF19 -> 1360.0105
B4: % of COGS | C4: =C3/C19 -> 0.0033396282 | D4: =D3/D19 -> 0 | E4: =E3/E19 -> 0 | F4: =F3/F19 -> 0 | G4: =G3/G19 -> 0 | H4: =H3/H19 -> 0.0049729507 | I4: =I3/I19 -> 0 | J4: =J3/J19 -> 0 | ... W4: =W3/W19 -> 0.0055206143 | AB4: 0.0054 | AC4: 0.0054 | AD4: 0.0054 | AE4: 0.0054 | AF4: 0.0054
B5: Trade payables | C5: =C6+C7 -> 35067.55 | D5: =D6+D7 -> 0 | E5: =E6+E7 -> 0 | F5: =F6+F7 -> 0 | G5: =G6+G7 -> 0 | H5: =H6+H7 -> 40873.45 | I5: =I6+I7 -> 0 | J5: =J6+J7 -> 0 | ... W5: =W6+W7 -> 43559.91 | AB5: =AB19*AB22/365 -> 49780.387 | AC5: =AC19*AC22/365 -> 52735.902 | AD5: =AD19*AD22/365 -> 55689.113 | AE5: =AE19*AE22/365 -> 58807.703 | AF5: =AF19*AF22/365 -> 62100.934
B6: Total outstanding dues of micro enterprises and small enterprises | C6: ='Balance Sheet'!C56 -> 1213.83 | D6: ='Balance Sheet'!D56 -> 0 | E6: ='Balance Sheet'!E56 -> 0 | F6: ='Balance Sheet'!F56 -> 0 | G6: ='Balance Sheet'!G56 -> 0 | H6: ='Balance Sheet'!H56 -> 3369.6 | I6: ='Balance Sheet'!I56 -> 0 | J6: ='Balance Sheet'!J56 -> 0 | ... W6: ='Balance Sheet'!W56 -> 5606.74
B7: Total outstanding dues of creditors other than micro enterprises and small enterprises | C7: ='Balance Sheet'!C57 -> 33853.72 | D7: ='Balance Sheet'!D57 -> 0 | E7: ='Balance Sheet'!E57 -> 0 | F7: ='Balance Sheet'!F57 -> 0 | G7: ='Balance Sheet'!G57 -> 0 | H7: ='Balance Sheet'!H57 -> 37503.85 | I7: ='Balance Sheet'!I57 -> 0 | J7: ='Balance Sheet'!J57 -> 0 | ... W7: ='Balance Sheet'!W57 -> 37953.17
B8: Other financial liabilities | C8: ='Balance Sheet'!C58 -> 5632.76 | D8: ='Balance Sheet'!D58 -> 0 | E8: ='Balance Sheet'!E58 -> 0 | F8: ='Balance Sheet'!F58 -> 0 | G8: ='Balance Sheet'!G58 -> 0 | H8: ='Balance Sheet'!H58 -> 4644.64 | I8: ='Balance Sheet'!I58 -> 0 | J8: ='Balance Sheet'!J58 -> 0 | ... W8: ='Balance Sheet'!W58 -> 12578.92 | AB8: =AB9*AB19 -> 10094.356 | AC8: =AC9*AC19 -> 10693.669 | AD8: =AD9*AD19 -> 11292.515 | AE8: =AE9*AE19 -> 11924.895 | AF8: =AF9*AF19 -> 12592.689
B9: % of COGS | C9: =C8/C19 -> 0.040600272 | D9: =D8/D19 -> 0 | E9: =E8/E19 -> 0 | F9: =F8/F19 -> 0 | G9: =G8/G19 -> 0 | H9: =H8/H19 -> 0.029014855 | I9: =I8/I19 -> 0 | J9: =J8/J19 -> 0 | ... W9: =W8/W19 -> 0.066616815 | AB9: 0.05 | AC9: 0.05 | AD9: 0.05 | AE9: 0.05 | AF9: 0.05
B10: Liabilities for current tax net | C10: ='Balance Sheet'!C61 -> 2369.56 | D10: ='Balance Sheet'!D61 -> 0 | E10: ='Balance Sheet'!E61 -> 0 | F10: ='Balance Sheet'!F61 -> 0 | G10: ='Balance Sheet'!G61 -> 0 | H10: ='Balance Sheet'!H61 -> 1702.04 | I10: ='Balance Sheet'!I61 -> 0 | J10: ='Balance Sheet'!J61 -> 0 | ... W10: ='Balance Sheet'!W61 -> 1783.41 | AB10: =AB11*AB19 -> 2018.8712 | AC10: =AC11*AC19 -> 2138.7338 | AD10: =AD11*AD19 -> 2258.5029 | AE10: =AE11*AE19 -> 2384.9791 | AF10: =AF11*AF19 -> 2518.5379
B11: % of COGS | C11: =C10/C19 -> 0.01707951 | D11: =D10/D19 -> 0 | E11: =E10/E19 -> 0 | F11: =F10/F19 -> 0 | G11: =G10/G19 -> 0 | H11: =H10/H19 -> 0.010632567 | I11: =I10/I19 -> 0 | J11: =J10/J19 -> 0 | ... W11: =W10/W19 -> 0.0094447769 | AB11: 0.01 | AC11: 0.01 | AD11: 0.01 | AE11: 0.01 | AF11: 0.01
B12: Provisions | C12: ='Balance Sheet'!C60 -> 14284.79 | D12: ='Balance Sheet'!D60 -> 0 | E12: ='Balance Sheet'!E60 -> 0 | F12: ='Balance Sheet'!F60 -> 0 | G12: ='Balance Sheet'!G60 -> 0 | H12: ='Balance Sheet'!H60 -> 14641.92 | I12: ='Balance Sheet'!I60 -> 0 | J12: ='Balance Sheet'!J60 -> 0 | ... W12: ='Balance Sheet'!W60 -> 8532.38 | AB12: =AB13*AB19 -> 10094.356 | AC12: =AC13*AC19 -> 10693.669 | AD12: =AD13*AD19 -> 11292.515 | AE12: =AE13*AE19 -> 11924.895 | AF12: =AF13*AF19 -> 12592.689
B13: % of COGS | C13: =C12/C19 -> 0.10296309 | D13: =D12/D19 -> 0 | E13: =E12/E19 -> 0 | F13: =F12/F19 -> 0 | G13: =G12/G19 -> 0 | H13: =H12/H19 -> 0.09146741 | I13: =I12/I19 -> 0 | J13: =J12/J19 -> 0 | ... W13: =W12/W19 -> 0.045186707 | AB13: 0.05 | AC13: 0.05 | AD13: 0.05 | AE13: 0.05 | AF13: 0.05
B14: Other current liabilities | C14: ='Balance Sheet'!C59 -> 3008.24 | D14: ='Balance Sheet'!D59 -> 0 | E14: ='Balance Sheet'!E59 -> 0 | F14: ='Balance Sheet'!F59 -> 0 | G14: ='Balance Sheet'!G59 -> 0 | H14: ='Balance Sheet'!H59 -> 2543.22 | I14: ='Balance Sheet'!I59 -> 0 | J14: ='Balance Sheet'!J59 -> 0 | ... W14: ='Balance Sheet'!W59 -> 4229.4 | AB14: =AB15*AB19 -> 4037.7425 | AC14: =AC15*AC19 -> 4277.4676 | AD14: =AD15*AD19 -> 4517.0058 | AE14: =AE15*AE19 -> 4769.9581 | AF14: =AF15*AF19 -> 5037.0758
B15: % of COGS | C15: =C14/C19 -> 0.021683041 | D15: =D14/D19 -> 0 | E15: =E14/E19 -> 0 | F15: =F14/F19 -> 0 | G15: =G14/G19 -> 0 | H15: =H14/H19 -> 0.01588738 | I15: =I14/I19 -> 0 | J15: =J14/J19 -> 0 | ... W15: =W14/W19 -> 0.022398517 | AB15: 0.02 | AC15: 0.02 | AD15: 0.02 | AE15: 0.02 | AF15: 0.02
B16: Total current liabilities (Ex. Borrowing & Derivatives financial Instruments) | C16: =C14+C12+C10+C8+C7+C6+C3 -> 60826.23 | D16: =D14+D12+D10+D8+D7+D6+D3 -> 0 | E16: =E14+E12+E10+E8+E7+E6+E3 -> 0 | F16: =F14+F12+F10+F8+F7+F6+F3 -> 0 | G16: =G14+G12+G10+G8+G7+G6+G3 -> 0 | H16: =H14+H12+H10+H8+H7+H6+H3 -> 65201.33 | I16: =I14+I12+I10+I8+I7+I6+I3 -> 0 | J16: =J14+J12+J10+J8+J7+J6+J3 -> 0 | ... AF16: =AF14+AF12+AF10+AF8+AF7+AF6+AF3 -> 34101.003
B19: COGS | C19: ='Income Statement'!C14 -> 138737 | D19: ='Income Statement'!D14 -> 33448 | E19: ='Income Statement'!E14 -> 35170 | F19: ='Income Statement'!F14 -> 47524 | G19: ='Income Statement'!G14 -> 43936 | H19: ='Income Statement'!H14 -> 160078 | I19: ='Income Statement'!I14 -> 42737 | J19: ='Income Statement'!J14 -> 41305 | ... AF19: ='Income Statement'!AF14 -> 251853.79
B20: Total revenue from operations | C20: ='Income Statement'!C5 -> 295080 | D20: ='Income Statement'!D5 -> 67167 | E20: ='Income Statement'!E5 -> 82645 | F20: ='Income Statement'!F5 -> 98848 | G20: ='Income Statement'!G5 -> 80068 | H20: ='Income Statement'!H5 -> 328728 | I20: ='Income Statement'!I5 -> 77964 | J20: ='Income Statement'!J5 -> 85574 | ... AF20: ='Income Statement'!AF5 -> 513987.33
B22: Payable Days | C22: =C5/C19*365 -> 92.258415 | D22: =D5/D19*365 -> 0 | E22: =E5/E19*365 -> 0 | F22: =F5/F19*365 -> 0 | G22: =G5/G19*365 -> 0 | H22: =H5/H19*365 -> 93.197124 | I22: =I5/I19*365 -> 0 | J22: =J5/J19*365 -> 0 | ... W22: =W5/W19*365 -> 84.2016 | AB22: 90 | AC22: 90 | AD22: 90 | AE22: 90 | AF22: 90
AB24: Inventory Days=((I1+I0)/2)/COGS*365
AB25: Inventory Days=((I1+I0)/(2*COGS)*365
AB26: Inventory Days=(I1/(2*COGS)*365)+ (I0/2*COGS)*365
AB27: Inventory Days - Io/(2*COGS)*365 = I1 /( 2*COGS)*365

Sheet Change in WC
B1: FY Mar Rs. Lakhs | C1: FY 2020-21 | D1: Q1 2021-22 | E1: Q2 2021-22 | F1: Q3 2021-22 | G1: Q4 2021-22 | H1: FY 2021-22 | I1: Q1 2022-23 | J1: Q2 2022-23 | K1: Q3 2022-23 | L1: Q4 2022-23 | M1: FY 2022-23 | N1: Q1 2023-24 | O1: Q2 2023-24 | P1: Q3 2023-24 | Q1: Q4 2023-24 | R1: FY 2023-24 | S1: Q1 2024-25 | T1: Q2 2024-25 | U1: Q3 2024-25 | V1: Q4 2024-25 | W1: FY 2024-25 | X1: Q1 2025-26 | Y1: E Q2 2025-26 | Z1: E Q3 2025-26 | AA1: E Q4 2025-26 | AB1: E FY 2025-26 | AC1: E FY 2026-27 | AD1: E FY 2027-28 | AE1: E FY 2028-29 | AF1: FY 2029-30
B3: Inventory Days | C3: ='Current Assets'!C20 -> 79.043782 | D3: ='Current Assets'!D20 -> 0 | E3: ='Current Assets'!E20 -> 0 | F3: ='Current Assets'!F20 -> 0 | G3: ='Current Assets'!G20 -> 0 | H3: ='Current Assets'!H20 -> 81.541011 | I3: ='Current Assets'!I20 -> 0 | J3: ='Current Assets'!J20 -> 0 | ... AF3: ='Current Assets'!AF20 -> 68
B4: Receivable Days | C4: ='Current Assets'!C21 -> 28.666762 | D4: ='Current Assets'!D21 -> 0 | E4: ='Current Assets'!E21 -> 0 | F4: ='Current Assets'!F21 -> 0 | G4: ='Current Assets'!G21 -> 0 | H4: ='Current Assets'!H21 -> 35.632902 | I4: ='Current Assets'!I21 -> 0 | J4: ='Current Assets'!J21 -> 0 | ... AF4: ='Current Assets'!AF21 -> 45
B5: Operating Cycle | C5: =C3+C4 -> 107.71054 | D5: =D3+D4 -> 0 | E5: =E3+E4 -> 0 | F5: =F3+F4 -> 0 | G5: =G3+G4 -> 0 | H5: =H3+H4 -> 117.17391 | I5: =I3+I4 -> 0 | J5: =J3+J4 -> 0 | ... AF5: =AF3+AF4 -> 113
B7: Payable Days | C7: ='Current Liability'!C22 -> 92.258415 | D7: ='Current Liability'!D22 -> 0 | E7: ='Current Liability'!E22 -> 0 | F7: ='Current Liability'!F22 -> 0 | G7: ='Current Liability'!G22 -> 0 | H7: ='Current Liability'!H22 -> 93.197124 | I7: ='Current Liability'!I22 -> 0 | J7: ='Current Liability'!J22 -> 0 | ... AF7: ='Current Liability'!AF22 -> 90
B8: Cash Convesrion Cycle | C8: =C5-C7 -> 15.452129 | D8: =D5-D7 -> 0 | E8: =E5-E7 -> 0 | F8: =F5-F7 -> 0 | G8: =G5-G7 -> 0 | H8: =H5-H7 -> 23.976789 | I8: =I5-I7 -> 0 | J8: =J5-J7 -> 0 | ... AF8: =AF5-AF7 -> 23
B10: Current Assets (Ex. Cash & Financial Derivatives) | C10: ='Current Assets'!C14 -> 110394.96 | D10: ='Current Assets'!D14 -> 0 | E10: ='Current Assets'!E14 -> 0 | F10: ='Current Assets'!F14 -> 0 | G10: ='Current Assets'!G14 -> 0 | H10: ='Current Assets'!H14 -> 104056.99 | I10: ='Current Assets'!I14 -> 0 | J10: ='Current Assets'!J14 -> 0 | ... AF10: ='Current Assets'!AF14 -> 207241.13
B11: Total current liabilities (Ex. Borrowing & Derivatives financial Instruments) | C11: ='Current Liability'!C16 -> 60826.23 | D11: ='Current Liability'!D16 -> 0 | E11: ='Current Liability'!E16 -> 0 | F11: ='Current Liability'!F16 -> 0 | G11: ='Current Liability'!G16 -> 0 | H11: ='Current Liability'!H16 -> 65201.33 | I11: ='Current Liability'!I16 -> 0 | J11: ='Current Liability'!J16 -> 0 | ... AF11: ='Current Liability'!AF16 -> 34101.003
B12: Working Capital | C12: =C10-C11 -> 49568.73 | D12: =D10-D11 -> 0 | E12: =E10-E11 -> 0 | F12: =F10-F11 -> 0 | G12: =G10-G11 -> 0 | H12: =H10-H11 -> 38855.66 | I12: =I10-I11 -> 0 | J12: =J10-J11 -> 0 | ... AF12: =AF10-AF11 -> 173140.12
B13: Change in Working Capital | H13: =H12-C12 -> -10713.07 | I13: =I12-D12 -> 0 | J13: =J12-E12 -> 0 | K13: =K12-F12 -> 0 | L13: =L12-G12 -> 0 | M13: =M12-H12 -> 19451.04 | N13: =N12-I12 -> 0 | O13: =O12-J12 -> 0 | ... AB13: =AB12-W12 -> 49612.774 | AC13: =AC12-AB12 -> 6705.1784 | AD13: =AD12-AC12 -> 8233.6802 | AE13: =AE12-AD12 -> 8694.7662 | AF13: =AF12-AE12 -> 9181.6732

Sheet D&A
B1: FY Mar Rs. Mn | C1: FY 2020-21 | D1: Q1 2021-22 | E1: Q2 2021-22 | F1: Q3 2021-22 | G1: Q4 2021-22 | H1: FY 2021-22 | I1: Q1 2022-23 | J1: Q2 2022-23 | K1: Q3 2022-23 | L1: Q4 2022-23 | M1: FY 2022-23 | N1: Q1 2023-24 | O1: Q2 2023-24 | P1: Q3 2023-24 | Q1: Q4 2023-24 | R1: FY 2023-24 | S1: Q1 2024-25 | T1: Q2 2024-25 | U1: Q3 2024-25 | V1: Q4 2024-25 | W1: FY 2024-25 | X1: Q1 2025-26 | Y1: E Q2 2025-26 | Z1: E Q3 2025-26 | AA1: E Q4 2025-26 | AB1: E FY 2025-26 | AC1: E FY 2026-27 | AD1: E FY 2027-28 | AE1: E FY 2028-29 | AF1: FY 2029-30
B3: Opening Property plant and equipment | H3: =C8 -> 71426.68 | I3: =D8 -> 0 | J3: =E8 -> 0 | K3: =F8 -> 0 | L3: =G8 -> 0 | M3: =H8 -> 68569.04 | N3: =I8 -> 0 | O3: =J8 -> 0 | ... AB3: =W8 -> 54454.75 | AC3: =AB8 -> 51288.241 | AD3: =AC8 -> 48852.876 | AE3: =AD8 -> 47042.639 | AF3: =AE8 -> 45766.887
B4: Capex | C4: =-'Cash Flow '!C49 -> 3369.02 | D4: =-'Cash Flow '!D49 -> 0 | E4: =-'Cash Flow '!E49 -> 0 | F4: =-'Cash Flow '!F49 -> 0 | G4: =-'Cash Flow '!G49 -> 0 | H4: =-'Cash Flow '!H49 -> 48356.16 | I4: =-'Cash Flow '!I49 -> 0 | J4: =-'Cash Flow '!J49 -> 0 | ... W4: =-'Cash Flow '!W49 -> 4457.43 | X4: ='Cash Flow '!X49 -> 0 | Y4: ='Cash Flow '!Y49 -> 0 | Z4: ='Cash Flow '!Z49 -> 0 | AA4: ='Cash Flow '!AA49 -> 0 | AB4: =W4+272 -> 4729.43 | AC4: =AB4+272 -> 5001.43 | AD4: =AC4+272 -> 5273.43 | AE4: =AD4+272 -> 5545.43 | AF4: =AE4+272 -> 5817.43
B6: Depreciation | C6: ='Income Statement'!C24 -> 9910 | D6: ='Income Statement'!D24 -> 2339 | E6: ='Income Statement'!E24 -> 2361 | F6: ='Income Statement'!F24 -> 2418 | G6: ='Income Statement'!G24 -> 2303 | H6: ='Income Statement'!H24 -> 9421 | I6: ='Income Statement'!I24 -> 2416 | J6: ='Income Statement'!J24 -> 2447 | ... AA6: ='Income Statement'!AA24 -> 0 | AB6: =AB7*AB3 -> 7895.9387 | AC6: =AC7*AC3 -> 7436.795 | AD6: =AD7*AD3 -> 7083.6671 | AE6: =AE7*AE3 -> 6821.1827 | AF6: =AF7*AF3 -> 6636.1985
B7: Dpe % of Op PPE | H7: =H6/H3 -> 0.13189749 | I7: =I6/I3 -> #DIV/0! | J7: =J6/J3 -> #DIV/0! | K7: =K6/K3 -> #DIV/0! | L7: =L6/L3 -> #DIV/0! | M7: =M6/M3 -> 0.14198828 | N7: =N6/N3 -> #DIV/0! | O7: =O6/O3 -> #DIV/0! | ... AA7: =AA6/AA3 -> #DIV/0! | AB7: 0.145 | AC7: 0.145 | AD7: 0.145 | AE7: 0.145 | AF7: 0.145
B8: Closing Property plant and equipment | C8: ='Balance Sheet'!C3 -> 71426.68 | D8: ='Balance Sheet'!D3 -> 0 | E8: ='Balance Sheet'!E3 -> 0 | F8: ='Balance Sheet'!F3 -> 0 | G8: ='Balance Sheet'!G3 -> 0 | H8: ='Balance Sheet'!H3 -> 68569.04 | I8: ='Balance Sheet'!I3 -> 0 | J8: ='Balance Sheet'!J3 -> 0 | ... AA8: ='Balance Sheet'!AA3 -> 0 | AB8: =AB3+AB4-AB6 -> 51288.241 | AC8: =AC3+AC4-AC6 -> 48852.876 | AD8: =AD3+AD4-AD6 -> 47042.639 | AE8: =AE3+AE4-AE6 -> 45766.887 | AF8: =AF3+AF4-AF6 -> 44948.118
D11: =D14-#REF! -> #REF! | E11: =E14-#REF! -> #REF! | F11: =F14-A14 -> 6026 | G11: =G14-B14 -> #VALUE! | I11: =I14-D14 -> 434 | J11: =J14-E14 -> -3681 | K11: =K14-F14 -> -3680 | L11: =L14-G14 -> -2141 | N11: =N14-I14 -> -4077 | O11: =O14-J14 -> -4 | P11: =P14-K14 -> -4 | Q11: =Q14-L14 -> -1586 | S11: =S14-N14 -> 4 | T11: =T14-O14 -> -112 | U11: =U14-P14 -> -14 | V11: =V14-Q14 -> -41
B12: Opening Goodwill & Intangible | H12: =C17 -> 35343.51 | I12: =D17 -> 0 | J12: =E17 -> 0 | K12: =F17 -> 0 | L12: =G17 -> 0 | M12: =H17 -> 58426.61 | N12: =I17 -> 0 | O12: =J17 -> 0 | ... AB12: =W17 -> 36040.5 | AC12: =AB17 -> 2536 | AD12: =AC17 -> -4441 | AE12: =AD17 -> -4341 | AF12: =AE17 -> -4241
B13: Capex | H13: 0 | M13: 0 | R13: 0 | W13: 0 | AB13: 0 | AC13: 0 | AD13: 0 | AE13: 0 | AF13: 0
B14: Amortization | C14: ='Income Statement'!C25 -> 26785 | D14: ='Income Statement'!D25 -> 5961 | E14: ='Income Statement'!E25 -> 6027 | F14: ='Income Statement'!F25 -> 6026 | G14: ='Income Statement'!G25 -> 6043 | H14: ='Income Statement'!H25 -> 24057 | I14: ='Income Statement'!I25 -> 6395 | J14: ='Income Statement'!J25 -> 2346 | ... AA14: ='Income Statement'!AA25 -> 0 | AB14: =W14+100 -> 9355 | AC14: =X14+100 -> 2378 | AD14: =AC14+100 -> 2478 | AE14: =AD14+100 -> 2578 | AF14: =AE14+100 -> 2678
B15: Goodwill | C15: ='Balance Sheet'!C6 -> 0 | D15: ='Balance Sheet'!D6 -> 0 | E15: ='Balance Sheet'!E6 -> 0 | F15: ='Balance Sheet'!F6 -> 0 | G15: ='Balance Sheet'!G6 -> 0 | H15: ='Balance Sheet'!H6 -> 2415.35 | I15: ='Balance Sheet'!I6 -> 0 | J15: ='Balance Sheet'!J6 -> 0 | ... AA15: ='Balance Sheet'!AA6 -> 0 | AB15: 6819 | AC15: 6819 | AD15: 6819 | AE15: 6819 | AF15: 6819
B16: Other intangible assets | C16: ='Balance Sheet'!C7 -> 35343.51 | D16: ='Balance Sheet'!D7 -> 0 | E16: ='Balance Sheet'!E7 -> 0 | F16: ='Balance Sheet'!F7 -> 0 | G16: ='Balance Sheet'!G7 -> 0 | H16: ='Balance Sheet'!H7 -> 56011.26 | I16: ='Balance Sheet'!I7 -> 0 | J16: ='Balance Sheet'!J7 -> 0 | ... AA16: ='Balance Sheet'!AA7 -> 0 | AB16: =AB17-AB15 -> -4283 | AC16: =AC17-AC15 -> -11260 | AD16: =AD17-AD15 -> -11160 | AE16: =AE17-AE15 -> -11060 | AF16: =AF17-AF15 -> -10960
B17: Closing Goodwill & Intangible | C17: =C15+C16 -> 35343.51 | D17: =D15+D16 -> 0 | E17: =E15+E16 -> 0 | F17: =F15+F16 -> 0 | G17: =G15+G16 -> 0 | H17: =H15+H16 -> 58426.61 | I17: =I15+I16 -> 0 | J17: =J15+J16 -> 0 | ... AA17: =AA15+AA16 -> 0 | AB17: =AB13+AB14-AB15 -> 2536 | AC17: =AC13+AC14-AC15 -> -4441 | AD17: =AD13+AD14-AD15 -> -4341 | AE17: =AE13+AE14-AE15 -> -4241 | AF17: =AF13+AF14-AF15 -> -4141
B19: D&A | C19: =C6+C15 -> 9910 | D19: =D6+D15 -> 2339 | E19: =E6+E15 -> 2361 | F19: =F6+F15 -> 2418 | G19: =G6+G15 -> 2303 | H19: =H6+H15 -> 11836.35 | I19: =I6+I15 -> 2416 | J19: =J6+J15 -> 2447 | ... AA19: =AA6+AA15 -> 0 | AB19: =AB6+AB14 -> 17250.939 | AC19: =AC6+AC14 -> 9814.795 | AD19: =AD6+AD14 -> 9561.6671 | AE19: =AE6+AE14 -> 9399.1827 | AF19: =AF6+AF14 -> 9314.1985
B20: Total Capex | C20: =C4+C13 -> 3369.02 | D20: =D4+D13 -> 0 | E20: =E4+E13 -> 0 | F20: =F4+F13 -> 0 | G20: =G4+G13 -> 0 | H20: =H4+H13 -> 48356.16 | I20: =I4+I13 -> 0 | J20: =J4+J13 -> 0 | ... AF20: =AF4+AF13 -> 5817.43

Sheet DEBT
B1: FY Mar Rs. Mn | C1: FY 2020-21 | D1: Q1 2021-22 | E1: Q2 2021-22 | F1: Q3 2021-22 | G1: Q4 2021-22 | H1: FY 2021-22 | I1: Q1 2022-23 | J1: Q2 2022-23 | K1: Q3 2022-23 | L1: Q4 2022-23 | M1: FY 2022-23 | N1: Q1 2023-24 | O1: Q2 2023-24 | P1: Q3 2023-24 | Q1: Q4 2023-24 | R1: FY 2023-24 | S1: Q1 2024-25 | T1: Q2 2024-25 | U1: Q3 2024-25 | V1: Q4 2024-25 | W1: FY 2024-25 | X1: Q1 2025-26 | Y1: E Q2 2025-26 | Z1: E Q3 2025-26 | AA1: E Q4 2025-26 | AB1: E FY 2025-26 | AC1: E FY 2026-27 | AD1: E FY 2027-28 | AE1: E FY 2028-29 | AF1: FY 2029-30
B3: Borrowings | C3: 0 | D3: 1 | E3: 2 | F3: 3 | G3: 4 | H3: 0 | I3: 6 | J3: 7 | K3: 8 | L3: 9 | M3: 0 | R3: 0 | W3: 0 | AB3: 0 | AC3: 0 | AD3: 0 | AE3: 0 | AF3: 0
B4: Provisions | C4: ='Balance Sheet'!C47 -> 2296.58 | D4: ='Balance Sheet'!D47 -> 0 | E4: ='Balance Sheet'!E47 -> 0 | F4: ='Balance Sheet'!F47 -> 0 | G4: ='Balance Sheet'!G47 -> 0 | H4: ='Balance Sheet'!H47 -> 2523.13 | I4: ='Balance Sheet'!I47 -> 0 | J4: ='Balance Sheet'!J47 -> 0 | ... AA4: ='Balance Sheet'!AA47 -> 0 | AB4: 2000 | AC4: 2000 | AD4: 2000 | AE4: 2000 | AF4: 2000
B5: Long Term Borrowing | C5: =C3+C4 -> 2296.58 | D5: =D3+D4 -> 1 | E5: =E3+E4 -> 2 | F5: =F3+F4 -> 3 | G5: =G3+G4 -> 4 | H5: =H3+H4 -> 2523.13 | I5: =I3+I4 -> 6 | J5: =J3+J4 -> 7 | ... AF5: =AF3+AF4 -> 2000
D6: =D7-#REF! -> #REF! | E6: =E7-#REF! -> #REF! | F6: =F7-A7 -> 0 | G6: =G7-B7 -> #VALUE!
B7: Borrowings | C7: ='Balance Sheet'!C53 -> 9190.93 | D7: ='Balance Sheet'!D53 -> 0 | E7: ='Balance Sheet'!E53 -> 0 | F7: ='Balance Sheet'!F53 -> 0 | G7: ='Balance Sheet'!G53 -> 0 | H7: ='Balance Sheet'!H53 -> 26371.12 | I7: ='Balance Sheet'!I53 -> 0 | J7: ='Balance Sheet'!J53 -> 0 | ... W7: ='Balance Sheet'!W53 -> 6208.47 | AB7: 7500 | AC7: 7500 | AD7: 7500 | AE7: 7500 | AF7: 7500
B8: Provisions | C8: ='Balance Sheet'!C60 -> 14284.79 | D8: ='Balance Sheet'!D60 -> 0 | E8: ='Balance Sheet'!E60 -> 0 | F8: ='Balance Sheet'!F60 -> 0 | G8: ='Balance Sheet'!G60 -> 0 | H8: ='Balance Sheet'!H60 -> 14641.92 | I8: ='Balance Sheet'!I60 -> 0 | J8: ='Balance Sheet'!J60 -> 0 | ... W8: ='Balance Sheet'!W60 -> 8532.38 | AB8: =W8+1700 -> 10232.38 | AC8: =AB8+1700 -> 11932.38 | AD8: =AC8+1700 -> 13632.38 | AE8: =AD8+1700 -> 15332.38 | AF8: =AE8+1700 -> 17032.38
B9: Short Term Borrowing | C9: =C7+C8 -> 23475.72 | D9: =D7+D8 -> 0 | E9: =E7+E8 -> 0 | F9: =F7+F8 -> 0 | G9: =G7+G8 -> 0 | H9: =H7+H8 -> 41013.04 | I9: =I7+I8 -> 0 | J9: =J7+J8 -> 0 | ... W9: =W7+W8 -> 14740.85 | AB9: =AB7+AB8 -> 17732.38 | AC9: =AC7+AC8 -> 19432.38 | AD9: =AD7+AD8 -> 21132.38 | AE9: =AE7+AE8 -> 22832.38 | AF9: =AF7+AF8 -> 24532.38
B10: Total Debt | C10: =C5+C9 -> 25772.3 | D10: =D5+D9 -> 1 | E10: =E5+E9 -> 2 | F10: =F5+F9 -> 3 | G10: =G5+G9 -> 4 | H10: =H5+H9 -> 43536.17 | I10: =I5+I9 -> 6 | J10: =J5+J9 -> 7 | ... AF10: =AF5+AF9 -> 26532.38
B12: Finance Cost | C12: ='Income Statement'!C31 -> 1327 | D12: ='Income Statement'!D31 -> 64 | E12: ='Income Statement'!E31 -> 78 | F12: ='Income Statement'!F31 -> 183 | G12: ='Income Statement'!G31 -> 182 | H12: ='Income Statement'!H31 -> 507 | I12: ='Income Statement'!I31 -> 249 | J12: ='Income Statement'!J31 -> 176 | ... AA12: ='Income Statement'!AA31 -> 0 | AB12: =AB10*AB14 -> 789.2952 | AC12: =AC10*AC14 -> 857.2952 | AD12: =AD10*AD14 -> 925.2952 | AE12: =AE10*AE14 -> 993.2952 | AF12: =AF10*AF14 -> 1061.2952
B14: Interest Rate % | C14: =C12/C10 -> 0.05148939 | D14: =D12/D10 -> 64 | E14: =E12/E10 -> 39 | F14: =F12/F10 -> 61 | G14: =G12/G10 -> 45.5 | H14: =H12/H10 -> 0.011645489 | I14: =I12/I10 -> 41.5 | J14: =J12/J10 -> 25.142857 | ... AA14: =AA12/AA10 -> #DIV/0! | AB14: 0.04 | AC14: 0.04 | AD14: 0.04 | AE14: 0.04 | AF14: 0.04

Sheet Equity Scheduled
B1: FY Mar Rs. Mn | C1: FY 2020-21 | D1: Q1 2021-22 | E1: Q2 2021-22 | F1: Q3 2021-22 | G1: Q4 2021-22 | H1: FY 2021-22 | I1: Q1 2022-23 | J1: Q2 2022-23 | K1: Q3 2022-23 | L1: Q4 2022-23 | M1: FY 2022-23 | N1: Q1 2023-24 | O1: Q2 2023-24 | P1: Q3 2023-24 | Q1: Q4 2023-24 | R1: FY 2023-24 | S1: Q1 2024-25 | T1: Q2 2024-25 | U1: Q3 2024-25 | V1: Q4 2024-25 | W1: FY 2024-25 | X1: Q1 2025-26 | Y1: E Q2 2025-26 | Z1: E Q3 2025-26 | AA1: E Q4 2025-26 | AB1: E FY 2025-26 | AC1: E FY 2026-27 | AD1: E FY 2027-28 | AE1: E FY 2028-29 | AF1: FY 2029-30
B3: Equity share capital | C3: ='Balance Sheet'!C36 -> 4445.14 | D3: ='Balance Sheet'!D36 -> 0 | E3: ='Balance Sheet'!E36 -> 0 | F3: ='Balance Sheet'!F36 -> 0 | G3: ='Balance Sheet'!G36 -> 0 | H3: ='Balance Sheet'!H36 -> 4411.5 | I3: ='Balance Sheet'!I36 -> 0 | J3: ='Balance Sheet'!J36 -> 0 | ... W3: ='Balance Sheet'!W36 -> 4365 | AB3: 4365 | AC3: 4365 | AD3: 4365 | AE3: 4365 | AF3: 4365
B4: Other equity | C4: ='Balance Sheet'!C37 -> 171819.86 | D4: ='Balance Sheet'!D37 -> 0 | E4: ='Balance Sheet'!E37 -> 0 | F4: ='Balance Sheet'!F37 -> 0 | G4: ='Balance Sheet'!G37 -> 0 | H4: ='Balance Sheet'!H37 -> 203247.87 | I4: ='Balance Sheet'!I37 -> 0 | J4: ='Balance Sheet'!J37 -> 0 | ... W4: ='Balance Sheet'!W37 -> 265114.29 | AB4: =AB12 -> 310197 | AC4: =AC12 -> 362354.71 | AD4: =AD12 -> 417785.51 | AE4: =AE12 -> 476627.21 | AF4: =AF12 -> 539033.58
B5: Equity attributable to equity shareholders of the parent company | C5: ='Balance Sheet'!C38 -> 176265 | D5: ='Balance Sheet'!D38 -> 0 | E5: ='Balance Sheet'!E38 -> 0 | F5: ='Balance Sheet'!F38 -> 0 | G5: ='Balance Sheet'!G38 -> 0 | H5: ='Balance Sheet'!H38 -> 207659.37 | I5: ='Balance Sheet'!I38 -> 0 | J5: ='Balance Sheet'!J38 -> 0 | ... W5: ='Balance Sheet'!W38 -> 269479.29 | AB5: =AB3+AB4 -> 314562 | AC5: =AC3+AC4 -> 366719.71 | AD5: =AD3+AD4 -> 422150.51 | AE5: =AE3+AE4 -> 480992.21 | AF5: =AF3+AF4 -> 543398.58
B6: Non-Controlling interests | C6: ='Balance Sheet'!C39 -> -88.71 | D6: ='Balance Sheet'!D39 -> 0 | E6: ='Balance Sheet'!E39 -> 0 | F6: ='Balance Sheet'!F39 -> 0 | G6: ='Balance Sheet'!G39 -> 0 | H6: ='Balance Sheet'!H39 -> -230.09 | I6: ='Balance Sheet'!I39 -> 0 | J6: ='Balance Sheet'!J39 -> 0 | ... W6: ='Balance Sheet'!W39 -> -143.43 | AB6: 51 | AC6: 51 | AD6: 51 | AE6: 51 | AF6: 51
B7: Total equity | C7: ='Balance Sheet'!C40 -> 176176.29 | D7: ='Balance Sheet'!D40 -> 0 | E7: ='Balance Sheet'!E40 -> 0 | F7: ='Balance Sheet'!F40 -> 0 | G7: ='Balance Sheet'!G40 -> 0 | H7: ='Balance Sheet'!H40 -> 207429.28 | I7: ='Balance Sheet'!I40 -> 0 | J7: ='Balance Sheet'!J40 -> 0 | ... W7: ='Balance Sheet'!W40 -> 269335.86 | AB7: =AB5+AB6 -> 314613 | AC7: =AC5+AC6 -> 366770.71 | AD7: =AD5+AD6 -> 422201.51 | AE7: =AE5+AE6 -> 481043.21 | AF7: =AF5+AF6 -> 543449.58
B9: Opening other Equity | H9: =C12 -> 171819.86 | I9: =D12 -> 0 | J9: =E12 -> 0 | K9: =F12 -> 0 | L9: =G12 -> 0 | M9: =H12 -> 203247.87 | N9: =I12 -> 0 | O9: =J12 -> 0 | ... AB9: =W12 -> 265114.29 | AC9: =AB12 -> 310197 | AD9: =AC12 -> 362354.71 | AE9: =AD12 -> 417785.51 | AF9: =AE12 -> 476627.21
B10: Retain Earning | C10: =C15-C14 -> 9909.9 | D10: =D15-D14 -> 7779 | E10: =E15-E14 -> 18525 | F10: =F15-F14 -> 21952 | G10: =G15-G14 -> 35929 | H10: =H15-H14 -> 25590.9 | I10: =I15-I14 -> 33597 | J10: =J15-J14 -> 18013 | ... AF10: =AF15-AF14 -> 62406.374
B11: New Equity Share premium
B12: Cl Other Equity | C12: =C4 -> 171819.86 | D12: =D4 -> 0 | E12: =E4 -> 0 | F12: =F4 -> 0 | G12: =G4 -> 0 | H12: =H4 -> 203247.87 | I12: =I4 -> 0 | J12: =J4 -> 0 | ... AA12: =AA4 -> 0 | AB12: =AB9+AB10 -> 310197 | AC12: =AC9+AC10 -> 362354.71 | AD12: =AD9+AD10 -> 417785.51 | AE12: =AE9+AE10 -> 476627.21 | AF12: =AF9+AF10 -> 539033.58
B14: Dividend paid | C14: =-'Cash Flow '!C68 -> 35561.1 | D14: =-'Cash Flow '!D68 -> 0 | E14: =-'Cash Flow '!E68 -> 0 | F14: =-'Cash Flow '!F68 -> 0 | G14: =-'Cash Flow '!G68 -> 0 | H14: =-'Cash Flow '!H68 -> 35561.1 | I14: =-'Cash Flow '!I68 -> 0 | J14: =-'Cash Flow '!J68 -> 0 | ... AA14: =-'Cash Flow '!AA68 -> 0 | AB14: =AB15*AB17 -> 45082.71 | AC14: =AC15*AC17 -> 52157.715 | AD14: =AD15*AD17 -> 55430.791 | AE14: =AE15*AE17 -> 58841.705 | AF14: =AF15*AF17 -> 62406.374
B15: Net Profit | C15: ='Income Statement'!C38 -> 45471 | D15: ='Income Statement'!D38 -> 7779 | E15: ='Income Statement'!E38 -> 18525 | F15: ='Income Statement'!F38 -> 21952 | G15: ='Income Statement'!G38 -> 35929 | H15: ='Income Statement'!H38 -> 61152 | I15: ='Income Statement'!I38 -> 33597 | J15: ='Income Statement'!J38 -> 18013 | ... AF15: ='Income Statement'!AF38 -> 124812.75
B17: Dividend payout Ratio | C17: =C14/C15 -> 0.78206109 | D17: =D14/D15 -> 0 | E17: =E14/E15 -> 0 | F17: =F14/F15 -> 0 | G17: =G14/G15 -> 0 | H17: =H14/H15 -> 0.58151982 | I17: =I14/I15 -> 0 | J17: =J14/J15 -> 0 | ... AA17: =AA14/AA15 -> #DIV/0! | AB17: 0.5 | AC17: 0.5 | AD17: 0.5 | AE17: 0.5 | AF17: 0.5

Sheet FCFF
B1: FY Mar Rs. Mn | C1: FY 2020-21 | D1: Q1 2021-22 | E1: Q2 2021-22 | F1: Q3 2021-22 | G1: Q4 2021-22 | H1: FY 2021-22 | I1: Q1 2022-23 | J1: Q2 2022-23 | K1: Q3 2022-23 | L1: Q4 2022-23 | M1: FY 2022-23 | N1: Q1 2023-24 | O1: Q2 2023-24 | P1: Q3 2023-24 | Q1: Q4 2023-24 | R1: FY 2023-24 | S1: Q1 2024-25 | T1: Q2 2024-25 | U1: Q3 2024-25 | V1: Q4 2024-25 | W1: FY 2024-25 | X1: Q1 2025-26 | Y1: E Q2 2025-26 | Z1: E Q3 2025-26 | AA1: E Q4 2025-26 | AB1: E FY 2025-26 | AC1: E FY 2026-27 | AD1: E FY 2027-28 | AE1: E FY 2028-29 | AF1: FY 2029-30
B3: Net Profit | C3: ='Income Statement'!C38 -> 45471 | D3: ='Income Statement'!D38 -> 7779 | E3: ='Income Statement'!E38 -> 18525 | F3: ='Income Statement'!F38 -> 21952 | G3: ='Income Statement'!G38 -> 35929 | H3: ='Income Statement'!H38 -> 61152 | I3: ='Income Statement'!I38 -> 33597 | J3: ='Income Statement'!J38 -> 18013 | ... AF3: ='Income Statement'!AF38 -> 124812.75
B4: (Add) D&A | C4: ='Income Statement'!C26 -> 36695 | D4: ='Income Statement'!D26 -> 8300 | E4: ='Income Statement'!E26 -> 8388 | F4: ='Income Statement'!F26 -> 8444 | G4: ='Income Statement'!G26 -> 8346 | H4: ='Income Statement'!H26 -> 33478 | I4: ='Income Statement'!I26 -> 8811 | J4: ='Income Statement'!J26 -> 4793 | ... AF4: ='Income Statement'!AF26 -> 9314.1985
B5: (Add) Finance Cost*(1-T) | C5: ='Income Statement'!C31-(1-'Income Statement'!C37) -> 1326.2007 | D5: ='Income Statement'!D31-(1-'Income Statement'!D37) -> 63.183479 | E5: ='Income Statement'!E31-(1-'Income Statement'!E37) -> 77.18136 | F5: ='Income Statement'!F31-(1-'Income Statement'!F37) -> 182.18276 | G5: ='Income Statement'!G31-(1-'Income Statement'!G37) -> 178.51242 | H5: ='Income Statement'!H31-(1-'Income Statement'!H37) -> 506.11782 | I5: ='Income Statement'!I31-(1-'Income Statement'!I37) -> 244.78457 | J5: ='Income Statement'!J31-(1-'Income Statement'!J37) -> 175.02905 | ... AF5: ='Income Statement'!AF31-(1-'Income Statement'!AF37) -> 1060.3952
B6: (Less) Capex | C6: ='D&A'!C20 -> 3369.02 | D6: ='D&A'!D20 -> 0 | E6: ='D&A'!E20 -> 0 | F6: ='D&A'!F20 -> 0 | G6: ='D&A'!G20 -> 0 | H6: ='D&A'!H20 -> 48356.16 | I6: ='D&A'!I20 -> 0 | J6: ='D&A'!J20 -> 0 | ... AF6: ='D&A'!AF20 -> 5817.43
B7: (Less) Change in Working Capital | C7: ='Change in WC'!C13 -> 0 | D7: ='Change in WC'!D13 -> 0 | E7: ='Change in WC'!E13 -> 0 | F7: ='Change in WC'!F13 -> 0 | G7: ='Change in WC'!G13 -> 0 | H7: ='Change in WC'!H13 -> -10713.07 | I7: ='Change in WC'!I13 -> 0 | J7: ='Change in WC'!J13 -> 0 | ... AF7: ='Change in WC'!AF13 -> 9181.6732
B8: FCFF | C8: =C3+C4+C5-C6-C7 -> 80123.181 | D8: =D3+D4+D5-D6-D7 -> 16142.183 | E8: =E3+E4+E5-E6-E7 -> 26990.181 | F8: =F3+F4+F5-F6-F7 -> 30578.183 | G8: =G3+G4+G5-G6-G7 -> 44453.512 | H8: =H3+H4+H5-H6-H7 -> 57493.028 | I8: =I3+I4+I5-I6-I7 -> 42652.785 | J8: =J3+J4+J5-J6-J7 -> 22981.029 | ... AF8: =AF3+AF4+AF5-AF6-AF7 -> 120188.24

Sheet WACC
B1: FY Mar Rs. Mn | C1: FY 2020-21 | D1: Q1 2021-22 | E1: Q2 2021-22 | F1: Q3 2021-22 | G1: Q4 2021-22 | H1: FY 2021-22 | I1: Q1 2022-23 | J1: Q2 2022-23 | K1: Q3 2022-23 | L1: Q4 2022-23 | M1: FY 2022-23 | N1: Q1 2023-24 | O1: Q2 2023-24 | P1: Q3 2023-24 | Q1: Q4 2023-24 | R1: FY 2023-24 | S1: Q1 2024-25 | T1: Q2 2024-25 | U1: Q3 2024-25 | V1: Q4 2024-25 | W1: FY 2024-25 | X1: Q1 2025-26 | Y1: E Q2 2025-26 | Z1: E Q3 2025-26 | AA1: E Q4 2025-26 | AB1: E FY 2025-26 | AC1: E FY 2026-27 | AD1: E FY 2027-28 | AE1: E FY 2028-29 | AF1: FY 2029-30
B3: Total Equity | C3: ='Balance Sheet'!C40 -> 176176.29 | D3: ='Balance Sheet'!D40 -> 0 | E3: ='Balance Sheet'!E40 -> 0 | F3: ='Balance Sheet'!F40 -> 0 | G3: ='Balance Sheet'!G40 -> 0 | H3: ='Balance Sheet'!H40 -> 207429.28 | I3: ='Balance Sheet'!I40 -> 0 | J3: ='Balance Sheet'!J40 -> 0 | ... AA3: ='Balance Sheet'!AA40 -> 422201.51 | AB3: ='Balance Sheet'!Y40 -> 314613 | AC3: ='Balance Sheet'!Z40 -> 366770.71 | AD3: ='Balance Sheet'!AA40 -> 422201.51 | AE3: ='Balance Sheet'!AB40 -> 481043.21 | AF3: ='Balance Sheet'!AC40 -> 543449.58
B4: Total Debt | C4: =DEBT!C10 -> 25772.3 | D4: =DEBT!D10 -> 1 | E4: =DEBT!E10 -> 2 | F4: =DEBT!F10 -> 3 | G4: =DEBT!G10 -> 4 | H4: =DEBT!H10 -> 43536.17 | I4: =DEBT!I10 -> 6 | J4: =DEBT!J10 -> 7 | ... AF4: =DEBT!AF10 -> 26532.38
B5: Total Capital | C5: =C3+C4 -> 201948.59 | D5: =D3+D4 -> 1 | E5: =E3+E4 -> 2 | F5: =F3+F4 -> 3 | G5: =G3+G4 -> 4 | H5: =H3+H4 -> 250965.45 | I5: =I3+I4 -> 6 | J5: =J3+J4 -> 7 | ... AF5: =AF3+AF4 -> 569981.96
B7: Calculation of Cost of Debt
B8: Interest Rate | C8: =DEBT!C14 -> 0.05148939 | D8: =DEBT!D14 -> 64 | E8: =DEBT!E14 -> 39 | F8: =DEBT!F14 -> 61 | G8: =DEBT!G14 -> 45.5 | H8: =DEBT!H14 -> 0.011645489 | I8: =DEBT!I14 -> 41.5 | J8: =DEBT!J14 -> 25.142857 | ... AF8: =DEBT!AF14 -> 0.04
B9: Tax Rate | C9: ='Income Statement'!C37 -> 0.20074879 | D9: ='Income Statement'!D37 -> 0.18347853 | E9: ='Income Statement'!E37 -> 0.1813602 | F9: ='Income Statement'!F37 -> 0.18275567 | G9: ='Income Statement'!G37 -> -2.4875752 | H9: ='Income Statement'!H37 -> 0.11781763 | I9: ='Income Statement'!I37 -> -3.2154329 | J9: ='Income Statement'!J37 -> 0.029053471 | ... AF9: ='Income Statement'!AF37 -> 0.1
B10: After Tax Cost of Debt | C10: =C8*(1-C9) -> 0.041152957 | D10: =D8*(1-D9) -> 52.257374 | E10: =E8*(1-E9) -> 31.926952 | F10: =F8*(1-F9) -> 49.851904 | G10: =G8*(1-G9) -> 158.68467 | H10: =H8*(1-H9) -> 0.010273445 | I10: =I8*(1-I9) -> 174.94046 | J10: =J8*(1-J9) -> 24.41237 | ... AF10: =AF8*(1-AF9) -> 0.036
B11: Weight Debt in Total Capital | C11: =C4/C5 -> 0.12761812 | D11: =D4/D5 -> 1 | E11: =E4/E5 -> 1 | F11: =F4/F5 -> 1 | G11: =G4/G5 -> 1 | H11: =H4/H5 -> 0.17347476 | I11: =I4/I5 -> 1 | J11: =J4/J5 -> 1 | ... AF11: =AF4/AF5 -> 0.046549508
B13: Calculation of Cost of Equity
B14: Risk Free Rate (10 Years Govt. Bond) | X14: 6.5 | Y14: 6.5 | Z14: 6.5 | AA14: 6.5 | AB14: 0.05
B15: Expected Market Premium | AB15: 0.12
B16: Market Risk Premium | AB16: =AB15-AB14 -> 0.07
B17: Beta of the Stock | AB17: 0.59
B18: Cost of Equity | AB18: =AB14+(AB16*AB17) -> 0.0913
B19: Weight of Equity in Total Capital | AB19: =AB3/AB5 -> 0.94098205
B22: Weighted Average Cost of Capital | AB22: =AB11*AB10+AB19*AB18 -> 0.088036307

Sheet DCF Valuation
B1: FY Mar Rs. Mn | C1: FY 2020-21 | D1: Q1 2021-22 | E1: Q2 2021-22 | F1: Q3 2021-22 | G1: Q4 2021-22 | H1: FY 2021-22 | I1: Q1 2022-23 | J1: Q2 2022-23 | K1: Q3 2022-23 | L1: Q4 2022-23 | M1: FY 2022-23 | N1: Q1 2023-24 | O1: Q2 2023-24 | P1: Q3 2023-24 | Q1: Q4 2023-24 | R1: FY 2023-24 | S1: Q1 2024-25 | T1: Q2 2024-25 | U1: Q3 2024-25 | V1: Q4 2024-25 | W1: FY 2024-25 | X1: Q1 2025-26 | Y1: E Q2 2025-26 | Z1: E Q3 2025-26 | AA1: E Q4 2025-26 | AB1: E FY 2025-26 | AC1: E FY 2026-27 | AD1: E FY 2027-28 | AE1: E FY 2028-29 | AF1: FY 2029-30
B2: Yr | AB2: 0 | AC2: 1 | AD2: 2 | AE2: 3 | AF2: 4
B3: FCFF | X3: 19690 | Y3: 0 | Z3: 0 | AA3: 0 | AB3: =FCFF!AB8 -> 53862.549 | AC3: =FCFF!AC8 -> 103280.01 | AD3: =FCFF!AD8 -> 107840.53 | AE3: =FCFF!AE8 -> 113834.79 | AF3: =FCFF!AF8 -> 120188.24
B5: Terminal Value (T.V. nth yr) = FCFF n+1 / [ K-g ] | AF5: =AF3/(AB7-AB8) -> 3159829.3
B7: Cost of Capital = K | AB7: =WACC!AB22 -> 0.088036307
B8: Economic Growth = g | AB8: =WACC!AB14 -> 0.05
B10: Total Cash Flow = FCFF + Terminal Value | AB10: =AB3+AB5 -> 53862.549 | AC10: =AC3+AC5 -> 103280.01 | AD10: =AD3+AD5 -> 107840.53 | AE10: =AE3+AE5 -> 113834.79 | AF10: =AF3+AF5 -> 3280017.5
B12: PV of Future Cash Flow | AB12: =AB10/(1+$AB$7)^AB2 -> 53862.549 | AC12: =AC10/(1+$AB$7)^AC2 -> 94923.314 | AD12: =AD10/(1+$AB$7)^AD2 -> 91095.15 | AE12: =AE10/(1+$AB$7)^AE2 -> 88378.139 | AF12: =AF10/(1+$AB$7)^AF2 -> 2340467.5
B14: Final DCF Valuation | AB14: =SUM(AB12:AF12) -> 2668726.7
B16: No. of Outstanding Shares | AB16: 4360 | AC16: 4360 | AD16: 4360 | AE16: 4360 | AF16: 4360
B18: Intrinsic Value Per Share | AB18: =AB14/AB16 -> 612.09327
B20: EPS | AB20: ='Income Statement'!AB38/'DCF Valuation'!AB16 -> 20.680142 | AC20: ='Income Statement'!AC38/'DCF Valuation'!AC16 -> 23.925557 | AD20: ='Income Statement'!AD38/'DCF Valuation'!AD16 -> 25.426968 | AE20: ='Income Statement'!AE38/'DCF Valuation'!AE16 -> 26.991608 | AF20: ='Income Statement'!AF38/'DCF Valuation'!AF16 -> 28.626777
B22: PE Multiple | AB22: 29 | AC22: 29 | AD22: 29 | AE22: 29 | AF22: 29
B24: Valuation as per PE Multiple | W24: 480 | AB24: =AB20*AB22 -> 599.72412 | AC24: =AC20*AC22 -> 693.84116 | AD24: =AD20*AD22 -> 737.38209 | AE24: =AE20*AE22 -> 782.75663 | AF24: =AF20*AF22 -> 830.17653
W25: =IF(W24<AB18,"Undervalued","Overvalued") -> Undervalued
